Workbook

Sheet Cover
B2: Project Trailhead — Hypothetical Strategic Combination
B3: VF Corporation (NYSE: VFC, Acquirer) to acquire Under Armour, Inc. (NYSE: UAA, Target)
B5: Sector: Branded Apparel & Footwear | $ in millions except per-share data, unless noted
B7: IMPORTANT: This is a HYPOTHETICAL transaction. Neither company has proposed or announced this deal.
B8: Built for illustrative financial-modeling purposes on both companies' real reported financials. Not investment advice.
B10: Standalone Financials | C10: VFC and UAA standalone historicals (FY2025A) + 3-year projections, side by side
B11: Transaction & PPA | C11: Offer terms, consideration mix, sources & uses, purchase price allocation and goodwill
B12: Pro Forma & Accretion-Dilution | C12: Combined income statement, synergies phase-in, and EPS accretion/(dilution) vs. VFC standalone
B13: Sensitivity | C13: Accretion/dilution sensitivity: stock/cash mix and synergies realization
B14: Sources & Assumptions | C14: Full citation list and explicit disclosure of every estimated input
B16: Color legend:
B17: Blue text | C17: hardcoded input / sourced actual
B18: Black text | C18: formula (same-sheet)
B19: Green text | C19: formula linking to another sheet
B20: Yellow fill | C20: key output / key assumption cell

Sheet Standalone Financials
A1: Standalone Financials — Acquirer (VFC) & Target (UAA)
A2: FY2025A actuals sourced from each company's Form 10-K / earnings releases; Year 1E-3E are illustrative normalized projections (see Sources & Assumptions).
A4: VF CORPORATION (Acquirer) — FY ends late March | G4: UNDER ARMOUR, INC. (Target) — FY ends late March
B5: FY2025A | C5: Year 1E | D5: Year 2E | E5: Year 3E | H5: FY2025A | I5: Year 1E | J5: Year 2E | K5: Year 3E
A6: Revenue | B6: 9500 | C6: =B6*(1+C7) -> 9690 | D6: =C6*(1+D7) -> 9980.7 | E6: =D6*(1+E7) -> 10280.121 | G6: Revenue | H6: 4966 | I6: =H6*(1+I7) -> 5015.66 | J6: =I6*(1+J7) -> 5166.1298 | K6: =J6*(1+K7) -> 5372.775
A7: % growth YoY | B7: n/a | C7: 0.02 | D7: 0.03 | E7: 0.03 | G7: % growth YoY | H7: n/a | I7: 0.01 | J7: 0.03 | K7: 0.04
A8: Adjusted EBITDA (memo) | B8: 903 | C8: =C6*C9 -> 949.62 | D8: =D6*D9 -> 1018.0314 | E8: =E6*E9 -> 1099.9729 | G8: Adjusted net income (memo) | H8: 135
A9: EBITDA margin % | B9: =B8/B6 -> 0.095052632 | C9: 0.098 | D9: 0.102 | E9: 0.107 | G9: Adjusted net margin % | H9: =H8/H6 -> 0.027184857 | I9: =I11*(1-I12)/I6 -> 0.018392395 | J9: =J11*(1-J12)/J6 -> 0.022647515 | K9: =K11*(1-K12)/K6 -> 0.026801792
A10: D&A | B10: 259.6 | C10: =C6*$B$10/$B$6 -> 264.792 | D10: =D6*$B$10/$B$6 -> 272.73576 | E10: =E6*$B$10/$B$6 -> 280.91783 | G10: Operating loss, GAAP (memo) | H10: -72
A11: Adjusted EBIT (memo, = EBITDA - D&A) | B11: =B8-B10 -> 643.4 | C11: =C8-C10 -> 684.828 | D11: =D8-D10 -> 745.29564 | E11: =E8-E10 -> 819.05511 | G11: Adjusted EBIT (memo — projected years only) | H11: n/a | I11: 102.5 | J11: 130 | K11: 160
A12: Interest expense, net | B12: -293 | C12: =B12*0.98 -> -287.14 | D12: =C12*0.98 -> -281.3972 | E12: =D12*0.98 -> -275.76926 | G12: Normalized cash tax rate (NOL-shielded) | H12: n/a | I12: 0.1 | J12: 0.1 | K12: 0.1
A13: Net income (income from continuing operations) | B13: 69.3 | C13: =(C11+C12)*(1-0.25) -> 298.266 | D13: =(D11+D12)*(1-0.25) -> 347.92383 | E13: =(E11+E12)*(1-0.25) -> 407.46439 | G13: Adjusted net income (used for EPS) | H13: =H8 -> 135 | I13: =I11*(1-I12) -> 92.25 | J13: =J11*(1-J12) -> 117 | K13: =K11*(1-K12) -> 144
A14: Diluted shares outstanding, mm | B14: 393.13 | C14: =$B$14 -> 393.13 | D14: =$B$14 -> 393.13 | E14: =$B$14 -> 393.13 | G14: Diluted shares outstanding, mm | H14: 429 | I14: =$H$14 -> 429 | J14: =$H$14 -> 429 | K14: =$H$14 -> 429
A15: Diluted EPS (as reported) | B15: =B13/B14 -> 0.17627757 | C15: =C13/C14 -> 0.7586956 | D15: =D13/D14 -> 0.88500962 | E15: =E13/E14 -> 1.0364622 | G15: Adjusted diluted EPS | H15: =H13/H14 -> 0.31468531 | I15: =I13/I14 -> 0.21503497 | J15: =J13/J14 -> 0.27272727 | K15: =K13/K14 -> 0.33566434
A17: NOTE: FY2025A net income/EPS for both companies are as-reported (VFC) or company-defined-adjusted (UAA) figures containing one-time and non-operating items not individually decomposed here (restructuring, discontinued operations, impairments, tax valuation allowances). The memo EBITDA/EBIT rows are contextual reference points, not a full walk to net income for FY2025A. Year 1E-3E projections build a clean, normalized bridge — standard practice when a base year is distorted by one-time items. See Sources & Assumptions for full detail and real disclosed guidance used to calibrate these assumptions (e.g., VFC's FY2026 disclosed ~7% operating margin; UAA's raised FY2026 adjusted operating income outlook of $95-110mm).

Sheet Transaction & PPA
A1: Transaction Terms, Sources & Uses, and Purchase Price Allocation
A3: OFFER TERMS
A4: UAA undisturbed share price | B4: 5.06 | D4: Source: UAA share price, Sept 8, 2026 market data.
A5: Offer premium | B5: 0.35 | D5: Assumption: in line with strategic-deal premiums for a turnaround target (typically 25%-45%).
A6: Offer price per share | B6: =B4*(1+B5) -> 6.831
A7: UAA diluted shares outstanding, mm | B7: ='Standalone Financials'!H14 -> 429
A8: Equity purchase price | B8: =B6*B7 -> 2930.499
A9: % cash consideration | B9: 0.5
A10: % stock consideration | B10: =1-B9 -> 0.5
A11: Estimated transaction fees, % of equity purchase price | B11: 0.015
A12: New acquisition debt interest rate | B12: 0.075 | D12: ESTIMATE — reflects VFC's elevated leverage/credit profile (Debt/Equity ~2.8x); consistent with the ~6.5% blended rate estimated on VFC's existing debt plus a modest new-issue premium.
A13: VF Corporation current share price | B13: 14.97 | D13: Source: VFC share price, Sept 2026 market data.
A15: SOURCES & USES
A16: USES
A17: Equity purchase price | B17: =B8 -> 2930.499
A18: Estimated transaction fees | B18: =B8*B11 -> 43.957485
A19: Total uses | B19: =SUM(B17:B18) -> 2974.4565
A21: SOURCES
A22: New acquisition debt (funds cash consideration + fees) | B22: =B8*B9+B19-B8 -> 1509.207
A23: New VF Corporation stock issued to UAA holders | B23: =B8*B10 -> 1465.2495
A24: Total sources | B24: =B22+B23 -> 2974.4565
A25: Check: sources = uses | B25: =B24-B19 -> 0
A27: New VFC shares issued, mm | B27: =B23/B13 -> 97.879058
A28: VFC pre-deal diluted shares, mm | B28: ='Standalone Financials'!B14 -> 393.13
A29: Pro forma combined diluted shares, mm | B29: =B27+B28 -> 491.00906
A30: New acquisition debt interest expense, $/yr | B30: =B22*B12 -> 113.19052
A32: PURCHASE PRICE ALLOCATION & GOODWILL
A33: Purchase price (equity value paid to UAA holders) | B33: =B8 -> 2930.499
A34: Less: book value of UAA net assets (total equity) | B34: =-1890 -> -1890
A35: Plus: fair value step-up — identifiable intangibles (brand, customer relationships) | B35: 400 | D35: ESTIMATE — illustrative fair-value step-up; amortized over an assumed 15-year useful life (see below).
A36: Less: deferred tax liability on step-up | B36: =-B35*0.25 -> -100
A37: Fair value of net identifiable assets acquired | B37: =-B34+B35+B36 -> 2190
A38: Goodwill (plug) | B38: =B8-B37 -> 740.499
A39: Intangible amortization period, years | B39: 15
A40: Incremental annual amortization from step-up, $/yr | B40: =B35/B39 -> 26.666667

Sheet Pro Forma & Accretion-Dilution
A1: Pro Forma Combined Income Statement & Accretion / (Dilution) Analysis
B3: FY2025A | C3: Year 1E | D3: Year 2E | E3: Year 3E
A5: COMBINED OPERATING RESULTS (pre-synergy)
A6: VFC standalone revenue | C6: ='Standalone Financials'!C6 -> 9690 | D6: ='Standalone Financials'!D6 -> 9980.7 | E6: ='Standalone Financials'!E6 -> 10280.121
A7: UAA standalone revenue | C7: ='Standalone Financials'!I6 -> 5015.66 | D7: ='Standalone Financials'!J6 -> 5166.1298 | E7: ='Standalone Financials'!K6 -> 5372.775
A8: Combined revenue | C8: =C6+C7 -> 14705.66 | D8: =D6+D7 -> 15146.83 | E8: =E6+E7 -> 15652.896
A9: VFC standalone Adjusted EBIT | C9: ='Standalone Financials'!C11 -> 684.828 | D9: ='Standalone Financials'!D11 -> 745.29564 | E9: ='Standalone Financials'!E11 -> 819.05511
A10: UAA standalone Adjusted EBIT | C10: ='Standalone Financials'!I11 -> 102.5 | D10: ='Standalone Financials'!J11 -> 130 | E10: ='Standalone Financials'!K11 -> 160
A11: Combined Adjusted EBIT (pre-synergy) | C11: =C9+C10 -> 787.328 | D11: =D9+D10 -> 875.29564 | E11: =E9+E10 -> 979.05511
A13: SYNERGIES & PURCHASE-ACCOUNTING ADJUSTMENTS
A14: Run-rate pretax cost synergies | B14: 75 | E14: ESTIMATE — illustrative sourcing/logistics/corporate-overhead synergies, typical for a scale combination in branded apparel (~0.5%-0.8% of combined revenue).
A15: Phase-in % | C15: 0.5 | D15: 1 | E15: 1
A16: Realized synergies | C16: =$B$14*C15 -> 37.5 | D16: =$B$14*D15 -> 75 | E16: =$B$14*E15 -> 75
A17: Less: incremental intangible amortization (from PPA step-up) | C17: =-'Transaction & PPA'!$B$40 -> -26.666667 | D17: =-'Transaction & PPA'!$B$40 -> -26.666667 | E17: =-'Transaction & PPA'!$B$40 -> -26.666667
A18: Combined Adjusted EBIT (post-synergy) | C18: =C11+C16+C17 -> 798.16133 | D18: =D11+D16+D17 -> 923.62897 | E18: =E11+E16+E17 -> 1027.3884
A20: FINANCING IMPACT
A21: Less: new acquisition debt interest expense | C21: =-'Transaction & PPA'!$B$30 -> -113.19052 | D21: =-'Transaction & PPA'!$B$30 -> -113.19052 | E21: =-'Transaction & PPA'!$B$30 -> -113.19052
A22: Less: VFC standalone interest expense (unchanged) | C22: ='Standalone Financials'!C12 -> -287.14 | D22: ='Standalone Financials'!D12 -> -281.3972 | E22: ='Standalone Financials'!E12 -> -275.76926
A23: Pro forma pretax income | C23: =C18+C21+C22 -> 397.83081 | D23: =D18+D21+D22 -> 529.04125 | E23: =E18+E21+E22 -> 638.42867
A24: Normalized tax rate | C24: 0.25 | D24: 0.25 | E24: 0.25
A25: Pro forma net income | C25: =C23*(1-C24) -> 298.37311 | D25: =D23*(1-D24) -> 396.78094 | E25: =E23*(1-E24) -> 478.8215
A27: ACCRETION / (DILUTION) ANALYSIS
A28: Pro forma diluted shares outstanding, mm | C28: ='Transaction & PPA'!$B$29 -> 491.00906 | D28: ='Transaction & PPA'!$B$29 -> 491.00906 | E28: ='Transaction & PPA'!$B$29 -> 491.00906
A29: Pro forma diluted EPS | C29: =C25/C28 -> 0.60767333 | D29: =D25/D28 -> 0.80809291 | E29: =E25/E28 -> 0.97517855
A30: VFC standalone diluted EPS (as if deal did not happen) | C30: ='Standalone Financials'!C15 -> 0.7586956 | D30: ='Standalone Financials'!D15 -> 0.88500962 | E30: ='Standalone Financials'!E15 -> 1.0364622
A31: Accretion / (dilution), $ | C31: =C29-C30 -> -0.15102227 | D31: =D29-D30 -> -0.076916708 | E31: =E29-E30 -> -0.061283674
A32: Accretion / (dilution), % | C32: =C31/C30 -> -0.19905516 | D32: =D31/D30 -> -0.08691059 | E32: =E31/E30 -> -0.059127745
A34: Reading the result: a POSITIVE %/​$ figure means the deal is ACCRETIVE to VFC shareholders (pro forma EPS exceeds VFC's standalone EPS); a NEGATIVE figure means DILUTIVE. Because the deal is financed with new debt AND newly issued VFC stock (see Transaction & PPA), the share-count dilution from the stock component is the primary drag against accretion from synergies and UAA's earnings contribution.

Sheet Sensitivity
A1: Accretion / (Dilution) Sensitivity — Year 1
A2: Both tables recompute the Year 1 (first full post-close year) pro forma EPS in closed form for each scenario.
A4: SENSITIVITY 1 — Cash/Stock Consideration Mix (rows) vs. Synergy Realization (columns)
A6: % Cash \ Synergy realized | B6: 0 | C6: 0.5 | D6: 1 | E6: 1.5 | F6: 2
A7: 0 | B7: =((((('Pro Forma & Accretion-Dilution'!$C$11+('Pro Forma & Accretion-Dilution'!$B$14*'Pro Forma & Accretion-Dilution'!$C$15*B$6)+'Pro Forma & Accretion-Dilution'!$C$17)-(('Transaction & PPA'!$B$8*($A7+'Transaction & PPA'!$B$11))*'Transaction & PPA'!$B$12)+'Pro Forma & Accretion-Dilution'!$C$22)*(1-'Pro Forma & Accretion-Dilution'!$C$24))/('Transaction & PPA'!$B$28+(('Transaction & PPA'!$B$8*(1-$A7))/'Transaction & PPA'!$B$13)))/'Pro Forma & Accretion-Dilution'!$C$30)-1 -> -0.21065623 | C7: =((((('Pro Forma & Accretion-Dilution'!$C$11+('Pro Forma & Accretion-Dilution'!$B$14*'Pro Forma & Accretion-Dilution'!$C$15*C$6)+'Pro Forma & Accretion-Dilution'!$C$17)-(('Transaction & PPA'!$B$8*($A7+'Transaction & PPA'!$B$11))*'Transaction & PPA'!$B$12)+'Pro Forma & Accretion-Dilution'!$C$22)*(1-'Pro Forma & Accretion-Dilution'!$C$24))/('Transaction & PPA'!$B$28+(('Transaction & PPA'!$B$8*(1-$A7))/'Transaction & PPA'!$B$13)))/'Pro Forma & Accretion-Dilution'!$C$30)-1 -> -0.17918149 | D7: =((((('Pro Forma & Accretion-Dilution'!$C$11+('Pro Forma & Accretion-Dilution'!$B$14*'Pro Forma & Accretion-Dilution'!$C$15*D$6)+'Pro Forma & Accretion-Dilution'!$C$17)-(('Transaction & PPA'!$B$8*($A7+'Transaction & PPA'!$B$11))*'Transaction & PPA'!$B$12)+'Pro Forma & Accretion-Dilution'!$C$22)*(1-'Pro Forma & Accretion-Dilution'!$C$24))/('Transaction & PPA'!$B$28+(('Transaction & PPA'!$B$8*(1-$A7))/'Transaction & PPA'!$B$13)))/'Pro Forma & Accretion-Dilution'!$C$30)-1 -> -0.14770675 | E7: =((((('Pro Forma & Accretion-Dilution'!$C$11+('Pro Forma & Accretion-Dilution'!$B$14*'Pro Forma & Accretion-Dilution'!$C$15*E$6)+'Pro Forma & Accretion-Dilution'!$C$17)-(('Transaction & PPA'!$B$8*($A7+'Transaction & PPA'!$B$11))*'Transaction & PPA'!$B$12)+'Pro Forma & Accretion-Dilution'!$C$22)*(1-'Pro Forma & Accretion-Dilution'!$C$24))/('Transaction & PPA'!$B$28+(('Transaction & PPA'!$B$8*(1-$A7))/'Transaction & PPA'!$B$13)))/'Pro Forma & Accretion-Dilution'!$C$30)-1 -> -0.11623201 | F7: =((((('Pro Forma & Accretion-Dilution'!$C$11+('Pro Forma & Accretion-Dilution'!$B$14*'Pro Forma & Accretion-Dilution'!$C$15*F$6)+'Pro Forma & Accretion-Dilution'!$C$17)-(('Transaction & PPA'!$B$8*($A7+'Transaction & PPA'!$B$11))*'Transaction & PPA'!$B$12)+'Pro Forma & Accretion-Dilution'!$C$22)*(1-'Pro Forma & Accretion-Dilution'!$C$24))/('Transaction & PPA'!$B$28+(('Transaction & PPA'!$B$8*(1-$A7))/'Transaction & PPA'!$B$13)))/'Pro Forma & Accretion-Dilution'!$C$30)-1 -> -0.084757266
A8: 0.25 | B8: =((((('Pro Forma & Accretion-Dilution'!$C$11+('Pro Forma & Accretion-Dilution'!$B$14*'Pro Forma & Accretion-Dilution'!$C$15*B$6)+'Pro Forma & Accretion-Dilution'!$C$17)-(('Transaction & PPA'!$B$8*($A8+'Transaction & PPA'!$B$11))*'Transaction & PPA'!$B$12)+'Pro Forma & Accretion-Dilution'!$C$22)*(1-'Pro Forma & Accretion-Dilution'!$C$24))/('Transaction & PPA'!$B$28+(('Transaction & PPA'!$B$8*(1-$A8))/'Transaction & PPA'!$B$13)))/'Pro Forma & Accretion-Dilution'!$C$30)-1 -> -0.23970897 | C8: =((((('Pro Forma & Accretion-Dilution'!$C$11+('Pro Forma & Accretion-Dilution'!$B$14*'Pro Forma & Accretion-Dilution'!$C$15*C$6)+'Pro Forma & Accretion-Dilution'!$C$17)-(('Transaction & PPA'!$B$8*($A8+'Transaction & PPA'!$B$11))*'Transaction & PPA'!$B$12)+'Pro Forma & Accretion-Dilution'!$C$22)*(1-'Pro Forma & Accretion-Dilution'!$C$24))/('Transaction & PPA'!$B$28+(('Transaction & PPA'!$B$8*(1-$A8))/'Transaction & PPA'!$B$13)))/'Pro Forma & Accretion-Dilution'!$C$30)-1 -> -0.20538144 | D8: =((((('Pro Forma & Accretion-Dilution'!$C$11+('Pro Forma & Accretion-Dilution'!$B$14*'Pro Forma & Accretion-Dilution'!$C$15*D$6)+'Pro Forma & Accretion-Dilution'!$C$17)-(('Transaction & PPA'!$B$8*($A8+'Transaction & PPA'!$B$11))*'Transaction & PPA'!$B$12)+'Pro Forma & Accretion-Dilution'!$C$22)*(1-'Pro Forma & Accretion-Dilution'!$C$24))/('Transaction & PPA'!$B$28+(('Transaction & PPA'!$B$8*(1-$A8))/'Transaction & PPA'!$B$13)))/'Pro Forma & Accretion-Dilution'!$C$30)-1 -> -0.17105391 | E8: =((((('Pro Forma & Accretion-Dilution'!$C$11+('Pro Forma & Accretion-Dilution'!$B$14*'Pro Forma & Accretion-Dilution'!$C$15*E$6)+'Pro Forma & Accretion-Dilution'!$C$17)-(('Transaction & PPA'!$B$8*($A8+'Transaction & PPA'!$B$11))*'Transaction & PPA'!$B$12)+'Pro Forma & Accretion-Dilution'!$C$22)*(1-'Pro Forma & Accretion-Dilution'!$C$24))/('Transaction & PPA'!$B$28+(('Transaction & PPA'!$B$8*(1-$A8))/'Transaction & PPA'!$B$13)))/'Pro Forma & Accretion-Dilution'!$C$30)-1 -> -0.13672638 | F8: =((((('Pro Forma & Accretion-Dilution'!$C$11+('Pro Forma & Accretion-Dilution'!$B$14*'Pro Forma & Accretion-Dilution'!$C$15*F$6)+'Pro Forma & Accretion-Dilution'!$C$17)-(('Transaction & PPA'!$B$8*($A8+'Transaction & PPA'!$B$11))*'Transaction & PPA'!$B$12)+'Pro Forma & Accretion-Dilution'!$C$22)*(1-'Pro Forma & Accretion-Dilution'!$C$24))/('Transaction & PPA'!$B$28+(('Transaction & PPA'!$B$8*(1-$A8))/'Transaction & PPA'!$B$13)))/'Pro Forma & Accretion-Dilution'!$C$30)-1 -> -0.10239885
A9: 0.5 | B9: =((((('Pro Forma & Accretion-Dilution'!$C$11+('Pro Forma & Accretion-Dilution'!$B$14*'Pro Forma & Accretion-Dilution'!$C$15*B$6)+'Pro Forma & Accretion-Dilution'!$C$17)-(('Transaction & PPA'!$B$8*($A9+'Transaction & PPA'!$B$11))*'Transaction & PPA'!$B$12)+'Pro Forma & Accretion-Dilution'!$C$22)*(1-'Pro Forma & Accretion-Dilution'!$C$24))/('Transaction & PPA'!$B$28+(('Transaction & PPA'!$B$8*(1-$A9))/'Transaction & PPA'!$B$13)))/'Pro Forma & Accretion-Dilution'!$C$30)-1 -> -0.27455316 | C9: =((((('Pro Forma & Accretion-Dilution'!$C$11+('Pro Forma & Accretion-Dilution'!$B$14*'Pro Forma & Accretion-Dilution'!$C$15*C$6)+'Pro Forma & Accretion-Dilution'!$C$17)-(('Transaction & PPA'!$B$8*($A9+'Transaction & PPA'!$B$11))*'Transaction & PPA'!$B$12)+'Pro Forma & Accretion-Dilution'!$C$22)*(1-'Pro Forma & Accretion-Dilution'!$C$24))/('Transaction & PPA'!$B$28+(('Transaction & PPA'!$B$8*(1-$A9))/'Transaction & PPA'!$B$13)))/'Pro Forma & Accretion-Dilution'!$C$30)-1 -> -0.23680416 | D9: =((((('Pro Forma & Accretion-Dilution'!$C$11+('Pro Forma & Accretion-Dilution'!$B$14*'Pro Forma & Accretion-Dilution'!$C$15*D$6)+'Pro Forma & Accretion-Dilution'!$C$17)-(('Transaction & PPA'!$B$8*($A9+'Transaction & PPA'!$B$11))*'Transaction & PPA'!$B$12)+'Pro Forma & Accretion-Dilution'!$C$22)*(1-'Pro Forma & Accretion-Dilution'!$C$24))/('Transaction & PPA'!$B$28+(('Transaction & PPA'!$B$8*(1-$A9))/'Transaction & PPA'!$B$13)))/'Pro Forma & Accretion-Dilution'!$C$30)-1 -> -0.19905516 | E9: =((((('Pro Forma & Accretion-Dilution'!$C$11+('Pro Forma & Accretion-Dilution'!$B$14*'Pro Forma & Accretion-Dilution'!$C$15*E$6)+'Pro Forma & Accretion-Dilution'!$C$17)-(('Transaction & PPA'!$B$8*($A9+'Transaction & PPA'!$B$11))*'Transaction & PPA'!$B$12)+'Pro Forma & Accretion-Dilution'!$C$22)*(1-'Pro Forma & Accretion-Dilution'!$C$24))/('Transaction & PPA'!$B$28+(('Transaction & PPA'!$B$8*(1-$A9))/'Transaction & PPA'!$B$13)))/'Pro Forma & Accretion-Dilution'!$C$30)-1 -> -0.16130616 | F9: =((((('Pro Forma & Accretion-Dilution'!$C$11+('Pro Forma & Accretion-Dilution'!$B$14*'Pro Forma & Accretion-Dilution'!$C$15*F$6)+'Pro Forma & Accretion-Dilution'!$C$17)-(('Transaction & PPA'!$B$8*($A9+'Transaction & PPA'!$B$11))*'Transaction & PPA'!$B$12)+'Pro Forma & Accretion-Dilution'!$C$22)*(1-'Pro Forma & Accretion-Dilution'!$C$24))/('Transaction & PPA'!$B$28+(('Transaction & PPA'!$B$8*(1-$A9))/'Transaction & PPA'!$B$13)))/'Pro Forma & Accretion-Dilution'!$C$30)-1 -> -0.12355715
A10: 0.75 | B10: =((((('Pro Forma & Accretion-Dilution'!$C$11+('Pro Forma & Accretion-Dilution'!$B$14*'Pro Forma & Accretion-Dilution'!$C$15*B$6)+'Pro Forma & Accretion-Dilution'!$C$17)-(('Transaction & PPA'!$B$8*($A10+'Transaction & PPA'!$B$11))*'Transaction & PPA'!$B$12)+'Pro Forma & Accretion-Dilution'!$C$22)*(1-'Pro Forma & Accretion-Dilution'!$C$24))/('Transaction & PPA'!$B$28+(('Transaction & PPA'!$B$8*(1-$A10))/'Transaction & PPA'!$B$13)))/'Pro Forma & Accretion-Dilution'!$C$30)-1 -> -0.31711224 | C10: =((((('Pro Forma & Accretion-Dilution'!$C$11+('Pro Forma & Accretion-Dilution'!$B$14*'Pro Forma & Accretion-Dilution'!$C$15*C$6)+'Pro Forma & Accretion-Dilution'!$C$17)-(('Transaction & PPA'!$B$8*($A10+'Transaction & PPA'!$B$11))*'Transaction & PPA'!$B$12)+'Pro Forma & Accretion-Dilution'!$C$22)*(1-'Pro Forma & Accretion-Dilution'!$C$24))/('Transaction & PPA'!$B$28+(('Transaction & PPA'!$B$8*(1-$A10))/'Transaction & PPA'!$B$13)))/'Pro Forma & Accretion-Dilution'!$C$30)-1 -> -0.27518421 | D10: =((((('Pro Forma & Accretion-Dilution'!$C$11+('Pro Forma & Accretion-Dilution'!$B$14*'Pro Forma & Accretion-Dilution'!$C$15*D$6)+'Pro Forma & Accretion-Dilution'!$C$17)-(('Transaction & PPA'!$B$8*($A10+'Transaction & PPA'!$B$11))*'Transaction & PPA'!$B$12)+'Pro Forma & Accretion-Dilution'!$C$22)*(1-'Pro Forma & Accretion-Dilution'!$C$24))/('Transaction & PPA'!$B$28+(('Transaction & PPA'!$B$8*(1-$A10))/'Transaction & PPA'!$B$13)))/'Pro Forma & Accretion-Dilution'!$C$30)-1 -> -0.23325619 | E10: =((((('Pro Forma & Accretion-Dilution'!$C$11+('Pro Forma & Accretion-Dilution'!$B$14*'Pro Forma & Accretion-Dilution'!$C$15*E$6)+'Pro Forma & Accretion-Dilution'!$C$17)-(('Transaction & PPA'!$B$8*($A10+'Transaction & PPA'!$B$11))*'Transaction & PPA'!$B$12)+'Pro Forma & Accretion-Dilution'!$C$22)*(1-'Pro Forma & Accretion-Dilution'!$C$24))/('Transaction & PPA'!$B$28+(('Transaction & PPA'!$B$8*(1-$A10))/'Transaction & PPA'!$B$13)))/'Pro Forma & Accretion-Dilution'!$C$30)-1 -> -0.19132816 | F10: =((((('Pro Forma & Accretion-Dilution'!$C$11+('Pro Forma & Accretion-Dilution'!$B$14*'Pro Forma & Accretion-Dilution'!$C$15*F$6)+'Pro Forma & Accretion-Dilution'!$C$17)-(('Transaction & PPA'!$B$8*($A10+'Transaction & PPA'!$B$11))*'Transaction & PPA'!$B$12)+'Pro Forma & Accretion-Dilution'!$C$22)*(1-'Pro Forma & Accretion-Dilution'!$C$24))/('Transaction & PPA'!$B$28+(('Transaction & PPA'!$B$8*(1-$A10))/'Transaction & PPA'!$B$13)))/'Pro Forma & Accretion-Dilution'!$C$30)-1 -> -0.14940014
A11: 1 | B11: =((((('Pro Forma & Accretion-Dilution'!$C$11+('Pro Forma & Accretion-Dilution'!$B$14*'Pro Forma & Accretion-Dilution'!$C$15*B$6)+'Pro Forma & Accretion-Dilution'!$C$17)-(('Transaction & PPA'!$B$8*($A11+'Transaction & PPA'!$B$11))*'Transaction & PPA'!$B$12)+'Pro Forma & Accretion-Dilution'!$C$22)*(1-'Pro Forma & Accretion-Dilution'!$C$24))/('Transaction & PPA'!$B$28+(('Transaction & PPA'!$B$8*(1-$A11))/'Transaction & PPA'!$B$13)))/'Pro Forma & Accretion-Dilution'!$C$30)-1 -> -0.3702674 | C11: =((((('Pro Forma & Accretion-Dilution'!$C$11+('Pro Forma & Accretion-Dilution'!$B$14*'Pro Forma & Accretion-Dilution'!$C$15*C$6)+'Pro Forma & Accretion-Dilution'!$C$17)-(('Transaction & PPA'!$B$8*($A11+'Transaction & PPA'!$B$11))*'Transaction & PPA'!$B$12)+'Pro Forma & Accretion-Dilution'!$C$22)*(1-'Pro Forma & Accretion-Dilution'!$C$24))/('Transaction & PPA'!$B$28+(('Transaction & PPA'!$B$8*(1-$A11))/'Transaction & PPA'!$B$13)))/'Pro Forma & Accretion-Dilution'!$C$30)-1 -> -0.32311989 | D11: =((((('Pro Forma & Accretion-Dilution'!$C$11+('Pro Forma & Accretion-Dilution'!$B$14*'Pro Forma & Accretion-Dilution'!$C$15*D$6)+'Pro Forma & Accretion-Dilution'!$C$17)-(('Transaction & PPA'!$B$8*($A11+'Transaction & PPA'!$B$11))*'Transaction & PPA'!$B$12)+'Pro Forma & Accretion-Dilution'!$C$22)*(1-'Pro Forma & Accretion-Dilution'!$C$24))/('Transaction & PPA'!$B$28+(('Transaction & PPA'!$B$8*(1-$A11))/'Transaction & PPA'!$B$13)))/'Pro Forma & Accretion-Dilution'!$C$30)-1 -> -0.27597238 | E11: =((((('Pro Forma & Accretion-Dilution'!$C$11+('Pro Forma & Accretion-Dilution'!$B$14*'Pro Forma & Accretion-Dilution'!$C$15*E$6)+'Pro Forma & Accretion-Dilution'!$C$17)-(('Transaction & PPA'!$B$8*($A11+'Transaction & PPA'!$B$11))*'Transaction & PPA'!$B$12)+'Pro Forma & Accretion-Dilution'!$C$22)*(1-'Pro Forma & Accretion-Dilution'!$C$24))/('Transaction & PPA'!$B$28+(('Transaction & PPA'!$B$8*(1-$A11))/'Transaction & PPA'!$B$13)))/'Pro Forma & Accretion-Dilution'!$C$30)-1 -> -0.22882487 | F11: =((((('Pro Forma & Accretion-Dilution'!$C$11+('Pro Forma & Accretion-Dilution'!$B$14*'Pro Forma & Accretion-Dilution'!$C$15*F$6)+'Pro Forma & Accretion-Dilution'!$C$17)-(('Transaction & PPA'!$B$8*($A11+'Transaction & PPA'!$B$11))*'Transaction & PPA'!$B$12)+'Pro Forma & Accretion-Dilution'!$C$22)*(1-'Pro Forma & Accretion-Dilution'!$C$24))/('Transaction & PPA'!$B$28+(('Transaction & PPA'!$B$8*(1-$A11))/'Transaction & PPA'!$B$13)))/'Pro Forma & Accretion-Dilution'!$C$30)-1 -> -0.18167735
A13: Base case (50% cash / 50% stock, 100% synergy realization) is highlighted. Reading the grid: more cash funding (higher row) reduces share dilution and pushes results toward accretion, but requires more new debt, which increases interest expense — the two effects trade off against each other.
A15: SENSITIVITY 2 — Offer Premium (rows) vs. % Cash Consideration (columns)
A17: Premium \ % Cash | B17: 0 | C17: 0.25 | D17: 0.5 | E17: 0.75 | F17: 1
A18: 0.2 | B18: =((((('Pro Forma & Accretion-Dilution'!$C$11+('Pro Forma & Accretion-Dilution'!$B$14*'Pro Forma & Accretion-Dilution'!$C$15)+'Pro Forma & Accretion-Dilution'!$C$17)-((('Transaction & PPA'!$B$4*(1+$A18)*'Transaction & PPA'!$B$7)*(B$17+'Transaction & PPA'!$B$11))*'Transaction & PPA'!$B$12)+'Pro Forma & Accretion-Dilution'!$C$22)*(1-'Pro Forma & Accretion-Dilution'!$C$24))/('Transaction & PPA'!$B$28+((('Transaction & PPA'!$B$4*(1+$A18)*'Transaction & PPA'!$B$7)*(1-B$17))/'Transaction & PPA'!$B$13)))/'Pro Forma & Accretion-Dilution'!$C$30)-1 -> -0.11438102 | C18: =((((('Pro Forma & Accretion-Dilution'!$C$11+('Pro Forma & Accretion-Dilution'!$B$14*'Pro Forma & Accretion-Dilution'!$C$15)+'Pro Forma & Accretion-Dilution'!$C$17)-((('Transaction & PPA'!$B$4*(1+$A18)*'Transaction & PPA'!$B$7)*(C$17+'Transaction & PPA'!$B$11))*'Transaction & PPA'!$B$12)+'Pro Forma & Accretion-Dilution'!$C$22)*(1-'Pro Forma & Accretion-Dilution'!$C$24))/('Transaction & PPA'!$B$28+((('Transaction & PPA'!$B$4*(1+$A18)*'Transaction & PPA'!$B$7)*(1-C$17))/'Transaction & PPA'!$B$13)))/'Pro Forma & Accretion-Dilution'!$C$30)-1 -> -0.133012 | D18: =((((('Pro Forma & Accretion-Dilution'!$C$11+('Pro Forma & Accretion-Dilution'!$B$14*'Pro Forma & Accretion-Dilution'!$C$15)+'Pro Forma & Accretion-Dilution'!$C$17)-((('Transaction & PPA'!$B$4*(1+$A18)*'Transaction & PPA'!$B$7)*(D$17+'Transaction & PPA'!$B$11))*'Transaction & PPA'!$B$12)+'Pro Forma & Accretion-Dilution'!$C$22)*(1-'Pro Forma & Accretion-Dilution'!$C$24))/('Transaction & PPA'!$B$28+((('Transaction & PPA'!$B$4*(1+$A18)*'Transaction & PPA'!$B$7)*(1-D$17))/'Transaction & PPA'!$B$13)))/'Pro Forma & Accretion-Dilution'!$C$30)-1 -> -0.15501905 | E18: =((((('Pro Forma & Accretion-Dilution'!$C$11+('Pro Forma & Accretion-Dilution'!$B$14*'Pro Forma & Accretion-Dilution'!$C$15)+'Pro Forma & Accretion-Dilution'!$C$17)-((('Transaction & PPA'!$B$4*(1+$A18)*'Transaction & PPA'!$B$7)*(E$17+'Transaction & PPA'!$B$11))*'Transaction & PPA'!$B$12)+'Pro Forma & Accretion-Dilution'!$C$22)*(1-'Pro Forma & Accretion-Dilution'!$C$24))/('Transaction & PPA'!$B$28+((('Transaction & PPA'!$B$4*(1+$A18)*'Transaction & PPA'!$B$7)*(1-E$17))/'Transaction & PPA'!$B$13)))/'Pro Forma & Accretion-Dilution'!$C$30)-1 -> -0.18141124 | F18: =((((('Pro Forma & Accretion-Dilution'!$C$11+('Pro Forma & Accretion-Dilution'!$B$14*'Pro Forma & Accretion-Dilution'!$C$15)+'Pro Forma & Accretion-Dilution'!$C$17)-((('Transaction & PPA'!$B$4*(1+$A18)*'Transaction & PPA'!$B$7)*(F$17+'Transaction & PPA'!$B$11))*'Transaction & PPA'!$B$12)+'Pro Forma & Accretion-Dilution'!$C$22)*(1-'Pro Forma & Accretion-Dilution'!$C$24))/('Transaction & PPA'!$B$28+((('Transaction & PPA'!$B$4*(1+$A18)*'Transaction & PPA'!$B$7)*(1-F$17))/'Transaction & PPA'!$B$13)))/'Pro Forma & Accretion-Dilution'!$C$30)-1 -> -0.21364428
A19: 0.275 | B19: =((((('Pro Forma & Accretion-Dilution'!$C$11+('Pro Forma & Accretion-Dilution'!$B$14*'Pro Forma & Accretion-Dilution'!$C$15)+'Pro Forma & Accretion-Dilution'!$C$17)-((('Transaction & PPA'!$B$4*(1+$A19)*'Transaction & PPA'!$B$7)*(B$17+'Transaction & PPA'!$B$11))*'Transaction & PPA'!$B$12)+'Pro Forma & Accretion-Dilution'!$C$22)*(1-'Pro Forma & Accretion-Dilution'!$C$24))/('Transaction & PPA'!$B$28+((('Transaction & PPA'!$B$4*(1+$A19)*'Transaction & PPA'!$B$7)*(1-B$17))/'Transaction & PPA'!$B$13)))/'Pro Forma & Accretion-Dilution'!$C$30)-1 -> -0.1313574 | C19: =((((('Pro Forma & Accretion-Dilution'!$C$11+('Pro Forma & Accretion-Dilution'!$B$14*'Pro Forma & Accretion-Dilution'!$C$15)+'Pro Forma & Accretion-Dilution'!$C$17)-((('Transaction & PPA'!$B$4*(1+$A19)*'Transaction & PPA'!$B$7)*(C$17+'Transaction & PPA'!$B$11))*'Transaction & PPA'!$B$12)+'Pro Forma & Accretion-Dilution'!$C$22)*(1-'Pro Forma & Accretion-Dilution'!$C$24))/('Transaction & PPA'!$B$28+((('Transaction & PPA'!$B$4*(1+$A19)*'Transaction & PPA'!$B$7)*(1-C$17))/'Transaction & PPA'!$B$13)))/'Pro Forma & Accretion-Dilution'!$C$30)-1 -> -0.1523247 | D19: =((((('Pro Forma & Accretion-Dilution'!$C$11+('Pro Forma & Accretion-Dilution'!$B$14*'Pro Forma & Accretion-Dilution'!$C$15)+'Pro Forma & Accretion-Dilution'!$C$17)-((('Transaction & PPA'!$B$4*(1+$A19)*'Transaction & PPA'!$B$7)*(D$17+'Transaction & PPA'!$B$11))*'Transaction & PPA'!$B$12)+'Pro Forma & Accretion-Dilution'!$C$22)*(1-'Pro Forma & Accretion-Dilution'!$C$24))/('Transaction & PPA'!$B$28+((('Transaction & PPA'!$B$4*(1+$A19)*'Transaction & PPA'!$B$7)*(1-D$17))/'Transaction & PPA'!$B$13)))/'Pro Forma & Accretion-Dilution'!$C$30)-1 -> -0.17728367 | E19: =((((('Pro Forma & Accretion-Dilution'!$C$11+('Pro Forma & Accretion-Dilution'!$B$14*'Pro Forma & Accretion-Dilution'!$C$15)+'Pro Forma & Accretion-Dilution'!$C$17)-((('Transaction & PPA'!$B$4*(1+$A19)*'Transaction & PPA'!$B$7)*(E$17+'Transaction & PPA'!$B$11))*'Transaction & PPA'!$B$12)+'Pro Forma & Accretion-Dilution'!$C$22)*(1-'Pro Forma & Accretion-Dilution'!$C$24))/('Transaction & PPA'!$B$28+((('Transaction & PPA'!$B$4*(1+$A19)*'Transaction & PPA'!$B$7)*(1-E$17))/'Transaction & PPA'!$B$13)))/'Pro Forma & Accretion-Dilution'!$C$30)-1 -> -0.20749413 | F19: =((((('Pro Forma & Accretion-Dilution'!$C$11+('Pro Forma & Accretion-Dilution'!$B$14*'Pro Forma & Accretion-Dilution'!$C$15)+'Pro Forma & Accretion-Dilution'!$C$17)-((('Transaction & PPA'!$B$4*(1+$A19)*'Transaction & PPA'!$B$7)*(F$17+'Transaction & PPA'!$B$11))*'Transaction & PPA'!$B$12)+'Pro Forma & Accretion-Dilution'!$C$22)*(1-'Pro Forma & Accretion-Dilution'!$C$24))/('Transaction & PPA'!$B$28+((('Transaction & PPA'!$B$4*(1+$A19)*'Transaction & PPA'!$B$7)*(1-F$17))/'Transaction & PPA'!$B$13)))/'Pro Forma & Accretion-Dilution'!$C$30)-1 -> -0.24480833
A20: 0.35 | B20: =((((('Pro Forma & Accretion-Dilution'!$C$11+('Pro Forma & Accretion-Dilution'!$B$14*'Pro Forma & Accretion-Dilution'!$C$15)+'Pro Forma & Accretion-Dilution'!$C$17)-((('Transaction & PPA'!$B$4*(1+$A20)*'Transaction & PPA'!$B$7)*(B$17+'Transaction & PPA'!$B$11))*'Transaction & PPA'!$B$12)+'Pro Forma & Accretion-Dilution'!$C$22)*(1-'Pro Forma & Accretion-Dilution'!$C$24))/('Transaction & PPA'!$B$28+((('Transaction & PPA'!$B$4*(1+$A20)*'Transaction & PPA'!$B$7)*(1-B$17))/'Transaction & PPA'!$B$13)))/'Pro Forma & Accretion-Dilution'!$C$30)-1 -> -0.14770675 | C20: =((((('Pro Forma & Accretion-Dilution'!$C$11+('Pro Forma & Accretion-Dilution'!$B$14*'Pro Forma & Accretion-Dilution'!$C$15)+'Pro Forma & Accretion-Dilution'!$C$17)-((('Transaction & PPA'!$B$4*(1+$A20)*'Transaction & PPA'!$B$7)*(C$17+'Transaction & PPA'!$B$11))*'Transaction & PPA'!$B$12)+'Pro Forma & Accretion-Dilution'!$C$22)*(1-'Pro Forma & Accretion-Dilution'!$C$24))/('Transaction & PPA'!$B$28+((('Transaction & PPA'!$B$4*(1+$A20)*'Transaction & PPA'!$B$7)*(1-C$17))/'Transaction & PPA'!$B$13)))/'Pro Forma & Accretion-Dilution'!$C$30)-1 -> -0.17105391 | D20: =((((('Pro Forma & Accretion-Dilution'!$C$11+('Pro Forma & Accretion-Dilution'!$B$14*'Pro Forma & Accretion-Dilution'!$C$15)+'Pro Forma & Accretion-Dilution'!$C$17)-((('Transaction & PPA'!$B$4*(1+$A20)*'Transaction & PPA'!$B$7)*(D$17+'Transaction & PPA'!$B$11))*'Transaction & PPA'!$B$12)+'Pro Forma & Accretion-Dilution'!$C$22)*(1-'Pro Forma & Accretion-Dilution'!$C$24))/('Transaction & PPA'!$B$28+((('Transaction & PPA'!$B$4*(1+$A20)*'Transaction & PPA'!$B$7)*(1-D$17))/'Transaction & PPA'!$B$13)))/'Pro Forma & Accretion-Dilution'!$C$30)-1 -> -0.19905516 | E20: =((((('Pro Forma & Accretion-Dilution'!$C$11+('Pro Forma & Accretion-Dilution'!$B$14*'Pro Forma & Accretion-Dilution'!$C$15)+'Pro Forma & Accretion-Dilution'!$C$17)-((('Transaction & PPA'!$B$4*(1+$A20)*'Transaction & PPA'!$B$7)*(E$17+'Transaction & PPA'!$B$11))*'Transaction & PPA'!$B$12)+'Pro Forma & Accretion-Dilution'!$C$22)*(1-'Pro Forma & Accretion-Dilution'!$C$24))/('Transaction & PPA'!$B$28+((('Transaction & PPA'!$B$4*(1+$A20)*'Transaction & PPA'!$B$7)*(1-E$17))/'Transaction & PPA'!$B$13)))/'Pro Forma & Accretion-Dilution'!$C$30)-1 -> -0.23325619 | F20: =((((('Pro Forma & Accretion-Dilution'!$C$11+('Pro Forma & Accretion-Dilution'!$B$14*'Pro Forma & Accretion-Dilution'!$C$15)+'Pro Forma & Accretion-Dilution'!$C$17)-((('Transaction & PPA'!$B$4*(1+$A20)*'Transaction & PPA'!$B$7)*(F$17+'Transaction & PPA'!$B$11))*'Transaction & PPA'!$B$12)+'Pro Forma & Accretion-Dilution'!$C$22)*(1-'Pro Forma & Accretion-Dilution'!$C$24))/('Transaction & PPA'!$B$28+((('Transaction & PPA'!$B$4*(1+$A20)*'Transaction & PPA'!$B$7)*(1-F$17))/'Transaction & PPA'!$B$13)))/'Pro Forma & Accretion-Dilution'!$C$30)-1 -> -0.27597238
A21: 0.425 | B21: =((((('Pro Forma & Accretion-Dilution'!$C$11+('Pro Forma & Accretion-Dilution'!$B$14*'Pro Forma & Accretion-Dilution'!$C$15)+'Pro Forma & Accretion-Dilution'!$C$17)-((('Transaction & PPA'!$B$4*(1+$A21)*'Transaction & PPA'!$B$7)*(B$17+'Transaction & PPA'!$B$11))*'Transaction & PPA'!$B$12)+'Pro Forma & Accretion-Dilution'!$C$22)*(1-'Pro Forma & Accretion-Dilution'!$C$24))/('Transaction & PPA'!$B$28+((('Transaction & PPA'!$B$4*(1+$A21)*'Transaction & PPA'!$B$7)*(1-B$17))/'Transaction & PPA'!$B$13)))/'Pro Forma & Accretion-Dilution'!$C$30)-1 -> -0.16346318 | C21: =((((('Pro Forma & Accretion-Dilution'!$C$11+('Pro Forma & Accretion-Dilution'!$B$14*'Pro Forma & Accretion-Dilution'!$C$15)+'Pro Forma & Accretion-Dilution'!$C$17)-((('Transaction & PPA'!$B$4*(1+$A21)*'Transaction & PPA'!$B$7)*(C$17+'Transaction & PPA'!$B$11))*'Transaction & PPA'!$B$12)+'Pro Forma & Accretion-Dilution'!$C$22)*(1-'Pro Forma & Accretion-Dilution'!$C$24))/('Transaction & PPA'!$B$28+((('Transaction & PPA'!$B$4*(1+$A21)*'Transaction & PPA'!$B$7)*(1-C$17))/'Transaction & PPA'!$B$13)))/'Pro Forma & Accretion-Dilution'!$C$30)-1 -> -0.18922569 | D21: =((((('Pro Forma & Accretion-Dilution'!$C$11+('Pro Forma & Accretion-Dilution'!$B$14*'Pro Forma & Accretion-Dilution'!$C$15)+'Pro Forma & Accretion-Dilution'!$C$17)-((('Transaction & PPA'!$B$4*(1+$A21)*'Transaction & PPA'!$B$7)*(D$17+'Transaction & PPA'!$B$11))*'Transaction & PPA'!$B$12)+'Pro Forma & Accretion-Dilution'!$C$22)*(1-'Pro Forma & Accretion-Dilution'!$C$24))/('Transaction & PPA'!$B$28+((('Transaction & PPA'!$B$4*(1+$A21)*'Transaction & PPA'!$B$7)*(1-D$17))/'Transaction & PPA'!$B$13)))/'Pro Forma & Accretion-Dilution'!$C$30)-1 -> -0.2203497 | E21: =((((('Pro Forma & Accretion-Dilution'!$C$11+('Pro Forma & Accretion-Dilution'!$B$14*'Pro Forma & Accretion-Dilution'!$C$15)+'Pro Forma & Accretion-Dilution'!$C$17)-((('Transaction & PPA'!$B$4*(1+$A21)*'Transaction & PPA'!$B$7)*(E$17+'Transaction & PPA'!$B$11))*'Transaction & PPA'!$B$12)+'Pro Forma & Accretion-Dilution'!$C$22)*(1-'Pro Forma & Accretion-Dilution'!$C$24))/('Transaction & PPA'!$B$28+((('Transaction & PPA'!$B$4*(1+$A21)*'Transaction & PPA'!$B$7)*(1-E$17))/'Transaction & PPA'!$B$13)))/'Pro Forma & Accretion-Dilution'!$C$30)-1 -> -0.25870329 | F21: =((((('Pro Forma & Accretion-Dilution'!$C$11+('Pro Forma & Accretion-Dilution'!$B$14*'Pro Forma & Accretion-Dilution'!$C$15)+'Pro Forma & Accretion-Dilution'!$C$17)-((('Transaction & PPA'!$B$4*(1+$A21)*'Transaction & PPA'!$B$7)*(F$17+'Transaction & PPA'!$B$11))*'Transaction & PPA'!$B$12)+'Pro Forma & Accretion-Dilution'!$C$22)*(1-'Pro Forma & Accretion-Dilution'!$C$24))/('Transaction & PPA'!$B$28+((('Transaction & PPA'!$B$4*(1+$A21)*'Transaction & PPA'!$B$7)*(1-F$17))/'Transaction & PPA'!$B$13)))/'Pro Forma & Accretion-Dilution'!$C$30)-1 -> -0.30713643
A22: 0.5 | B22: =((((('Pro Forma & Accretion-Dilution'!$C$11+('Pro Forma & Accretion-Dilution'!$B$14*'Pro Forma & Accretion-Dilution'!$C$15)+'Pro Forma & Accretion-Dilution'!$C$17)-((('Transaction & PPA'!$B$4*(1+$A22)*'Transaction & PPA'!$B$7)*(B$17+'Transaction & PPA'!$B$11))*'Transaction & PPA'!$B$12)+'Pro Forma & Accretion-Dilution'!$C$22)*(1-'Pro Forma & Accretion-Dilution'!$C$24))/('Transaction & PPA'!$B$28+((('Transaction & PPA'!$B$4*(1+$A22)*'Transaction & PPA'!$B$7)*(1-B$17))/'Transaction & PPA'!$B$13)))/'Pro Forma & Accretion-Dilution'!$C$30)-1 -> -0.17865836 | C22: =((((('Pro Forma & Accretion-Dilution'!$C$11+('Pro Forma & Accretion-Dilution'!$B$14*'Pro Forma & Accretion-Dilution'!$C$15)+'Pro Forma & Accretion-Dilution'!$C$17)-((('Transaction & PPA'!$B$4*(1+$A22)*'Transaction & PPA'!$B$7)*(C$17+'Transaction & PPA'!$B$11))*'Transaction & PPA'!$B$12)+'Pro Forma & Accretion-Dilution'!$C$22)*(1-'Pro Forma & Accretion-Dilution'!$C$24))/('Transaction & PPA'!$B$28+((('Transaction & PPA'!$B$4*(1+$A22)*'Transaction & PPA'!$B$7)*(1-C$17))/'Transaction & PPA'!$B$13)))/'Pro Forma & Accretion-Dilution'!$C$30)-1 -> -0.20686455 | D22: =((((('Pro Forma & Accretion-Dilution'!$C$11+('Pro Forma & Accretion-Dilution'!$B$14*'Pro Forma & Accretion-Dilution'!$C$15)+'Pro Forma & Accretion-Dilution'!$C$17)-((('Transaction & PPA'!$B$4*(1+$A22)*'Transaction & PPA'!$B$7)*(D$17+'Transaction & PPA'!$B$11))*'Transaction & PPA'!$B$12)+'Pro Forma & Accretion-Dilution'!$C$22)*(1-'Pro Forma & Accretion-Dilution'!$C$24))/('Transaction & PPA'!$B$28+((('Transaction & PPA'!$B$4*(1+$A22)*'Transaction & PPA'!$B$7)*(1-D$17))/'Transaction & PPA'!$B$13)))/'Pro Forma & Accretion-Dilution'!$C$30)-1 -> -0.24118281 | E22: =((((('Pro Forma & Accretion-Dilution'!$C$11+('Pro Forma & Accretion-Dilution'!$B$14*'Pro Forma & Accretion-Dilution'!$C$15)+'Pro Forma & Accretion-Dilution'!$C$17)-((('Transaction & PPA'!$B$4*(1+$A22)*'Transaction & PPA'!$B$7)*(E$17+'Transaction & PPA'!$B$11))*'Transaction & PPA'!$B$12)+'Pro Forma & Accretion-Dilution'!$C$22)*(1-'Pro Forma & Accretion-Dilution'!$C$24))/('Transaction & PPA'!$B$28+((('Transaction & PPA'!$B$4*(1+$A22)*'Transaction & PPA'!$B$7)*(1-E$17))/'Transaction & PPA'!$B$13)))/'Pro Forma & Accretion-Dilution'!$C$30)-1 -> -0.28384119 | F22: =((((('Pro Forma & Accretion-Dilution'!$C$11+('Pro Forma & Accretion-Dilution'!$B$14*'Pro Forma & Accretion-Dilution'!$C$15)+'Pro Forma & Accretion-Dilution'!$C$17)-((('Transaction & PPA'!$B$4*(1+$A22)*'Transaction & PPA'!$B$7)*(F$17+'Transaction & PPA'!$B$11))*'Transaction & PPA'!$B$12)+'Pro Forma & Accretion-Dilution'!$C$22)*(1-'Pro Forma & Accretion-Dilution'!$C$24))/('Transaction & PPA'!$B$28+((('Transaction & PPA'!$B$4*(1+$A22)*'Transaction & PPA'!$B$7)*(1-F$17))/'Transaction & PPA'!$B$13)))/'Pro Forma & Accretion-Dilution'!$C$30)-1 -> -0.33830048
A24: Simplification: this table holds the deal's goodwill/PPA-driven incremental amortization and combined pre-synergy EBIT constant across premium scenarios (a higher premium only changes purchase price / financing mix here, not the operating plan). Goodwill itself would technically grow with a higher premium; see Transaction & PPA tab to flex the premium assumption directly for a fully-updated goodwill figure.

Sheet Sources & Assumptions
A1: Sources & Assumptions — Full Disclosure
A3: This is a HYPOTHETICAL strategic combination — neither VF Corporation nor Under Armour has proposed or announced this transaction. Both companies' real FY2025A financials anchor the model; the deal terms, financing mix, purchase price allocation and projections are illustrative analyst assumptions. Direct access to SEC EDGAR / stockanalysis.com / press-release wires was blocked by this session's network egress policy, so every 'SOURCED' figure below was obtained via search-engine synthesis of the underlying filings/releases rather than a direct read of the primary document.
A5: # | B5: Item | C5: Detail / Citation
A6: SOURCED | B6: VFC FY2025A revenue & balance sheet | C6: Revenue $9.50bn (FY ended 3/29/2025, down 4.1% YoY); total assets $9,377.5mm; total liabilities $7,890.2mm; total equity $1,487.4mm; cash $429.4mm; LT debt $3,966.2mm + current portion $540.6mm — VFC FY2025 Form 10-K.
A7: SOURCED | B7: VFC income from continuing operations | C7: $69.3mm ($0.18/diluted share) — VFC FY2025 10-K. Effective tax rate 52.2% (anomalous — see below).
A8: SOURCED | B8: VFC D&A, shares, market data | C8: D&A $259.6mm (FY2025 10-K cash flow statement); ~393.13mm diluted shares; $14.97/share, ~$5.3-5.9bn market cap, Sept-2026 market data; EBITDA (TTM) ~$902.6mm.
A9: SOURCED | B9: VFC FY2026 (real, most-recently reported) directional color | C9: VFC's actual FY2026 (fiscal year ended ~March 2026) results, per company press release: revenue growth resumed (+1%), gross margin expanded to 55%, operating margin reached ~7%, and leverage improved by roughly one full turn. This real, more-recent data point is used only to calibrate the DIRECTION and rough magnitude of the Year 1E-3E margin-improvement assumptions built from the FY2025A base — it was not used to restate the FY2025A base year itself (kept anchored to the fully-disclosed, balance-sheet-reconciled FY2025A figures above).
A10: ESTIMATE | B10: VFC FY2025A interest expense ($293mm) | C10: Exact interest expense line not retrieved this session; derived as ~6.5% x total debt (~$4,507mm).
A11: SOURCED | B11: UAA FY2025A revenue & profitability | C11: Revenue $4.966bn (FY ended 3/31/2025, down from $5.31bn); operating loss $72mm (GAAP); net loss $201mm; adjusted net income $135mm; adjusted diluted EPS $0.31 — UAA FY2025 10-K / earnings release.
A12: SOURCED | B12: UAA FY2025A balance sheet | C12: Total assets $4.30bn; total equity $1.890bn; cash $501mm; no borrowings outstanding under its $1.1bn revolving credit facility — UAA FY2025 10-K.
A13: SOURCED | B13: UAA share count | C13: 188.83mm Class A + 34.45mm Class B + 205.54mm Class C = ~429mm total shares — UAA proxy/10-K disclosure, mid-2025; $5.06/share, ~$2.18bn market cap, Sept-2026 market data.
A14: SOURCED | B14: UAA FY2026E guidance (real, used to calibrate Year 1E) | C14: UAA 'raised FY2026 adjusted operating income outlook to $95-110mm' — a real, company-disclosed figure used directly as the Year 1E Adjusted EBIT anchor ($102.5mm midpoint) on the Standalone Financials tab, rather than an unmoored assumption.
A15: ASSUMPTION | B15: 35% offer premium -> $6.83/share offer price | C15: Illustrative premium for a strategic (not distressed) acquisition of a turnaround target; in line with recent branded-apparel/consumer strategic deal premiums (25%-45%).
A16: ASSUMPTION | B16: 50% cash / 50% stock consideration mix | C16: Illustrative — reflects VFC's constrained balance sheet (Debt/Equity ~2.8x) limiting an all-cash deal, balanced against management's likely reluctance to issue excessive new equity. Flex on the Transaction & PPA tab; see also the Sensitivity tab for how this choice drives accretion/dilution.
... A22: METHODOLOGY | B22: Sensitivity 2 (premium x cash%) simplification | C22: Holds the deal's incremental PPA amortization and combined pre-synergy EBIT constant as the premium varies (i.e., it flexes only price paid / financing mix, not the operating plan or goodwill). A higher premium would, in reality, also increase goodwill dollar-for-dollar; flex the premium assumption directly on the Transaction & PPA tab for a fully-updated PPA walk at any single premium level.
