Workbook

Sheet Cover
B2: Project Cracker Barrel — Hypothetical Sponsor LBO
B3: Leveraged Buyout of Cracker Barrel Old Country Store, Inc. (NASDAQ: CBRL)
B5: Fiscal year end: ~late July/early Aug | Sector: Family Dining / Restaurants | $ in millions unless noted
B7: IMPORTANT: This is a HYPOTHETICAL, illustrative transaction built on CBRL's real reported financials.
B8: No such buyout has been announced. Not investment advice. See Sources & Assumptions for every citation/estimate.
B10: Transaction Assumptions | C10: Entry, financing, operating & exit assumptions in one place
B11: Sources & Uses | C11: Purchase price build, financing sources, and uses of funds at close
B12: Debt Schedule | C12: 4-tranche debt stack (Revolver/TLA/TLB/Notes) with mandatory amortization + a dynamic cash-flow sweep
B13: Operating Model | C13: 5-year post-LBO income statement & free-cash-flow build
B14: Returns Analysis | C14: Exit equity value, IRR/MOIC, and 2-way sensitivity tables
B15: Sources & Assumptions | C15: Full citation list and explicit disclosure of every estimated input
B17: Color legend:
B18: Blue text | C18: hardcoded input / sourced actual
B19: Black text | C19: formula (same-sheet)
B20: Green text | C20: formula linking to another sheet
B21: Yellow fill | C21: key output / key assumption cell

Sheet Transaction Assumptions
A1: Transaction Assumptions
A3: ENTRY ASSUMPTIONS
A4: Current share price (undisturbed) | C4: 54.69 | I4: Source: CBRL closing price, referenced in fiscal 2025 earnings coverage (2026).
A5: Offer premium to undisturbed price | C5: 0.3 | I5: Assumption: in line with observed premiums in recent going-private restaurant/retail transactions (typically 25%-40%).
A6: Offer price per share | C6: =C4*(1+C5) -> 71.097
A7: Diluted shares outstanding, mm | C7: 22.35 | I7: Source: CBRL shares outstanding, 2025/2026 market data.
A8: FY2025A Adjusted EBITDA | C8: 224.3 | I8: Source: Cracker Barrel Q4/full-year fiscal 2025 earnings release — 'Adjusted EBITDA was $224.3mm, +9% YoY.'
A9: Existing net debt at close (refinanced) | C9: ='Sources & Uses'!B22 -> 472.6
A11: FINANCING ASSUMPTIONS (entry leverage, $mm, as multiple of FY25A Adj. EBITDA)
A12: Revolver — capacity (undrawn at close) | C12: 150
A13: Term Loan A — leverage (x EBITDA) | C13: 1 | I13: ESTIMATE — illustrative sponsor capital structure. ~4.5x total leverage is a moderate, defensible level for a real-estate-heavy restaurant chain with owned property (~$960mm net PP&E) supporting incremental debt capacity. Flex these cells on the Transaction Assumptions tab to stress-test a more/less aggressive structure.
A14: Term Loan B — leverage (x EBITDA) | C14: 2
A15: Senior Notes — leverage (x EBITDA) | C15: 1.5
A16: Total leverage (x EBITDA) | C16: =C13+C14+C15 -> 4.5
A17: Term Loan A rate (SOFR + spread) | C17: 0.07 | I17: ESTIMATE — illustrative spreads for a ~4.5x total-leverage sponsor deal in the current (Sept-2026) high-rate environment; SOFR proxy ~4.3%.
A18: Term Loan B rate (SOFR + spread) | C18: 0.0775
A19: Senior Notes fixed rate | C19: 0.085
A20: Revolver rate (SOFR + spread) | C20: 0.0675
A21: Term Loan A mandatory amortization, %/yr | C21: 0.05
A22: Term Loan B mandatory amortization, %/yr | C22: 0.01
A23: Cash flow sweep, % of excess FCF (to TLB, then TLA) | C23: 0.9
A24: Minimum cash balance | C24: 20
A25: Transaction fees & financing fees, % of total transaction value | C25: 0.02
A27: OPERATING ASSUMPTIONS (5-year hold)
A28: Revenue growth, % YoY | D28: 0.025 | E28: 0.03 | F28: 0.03 | G28: 0.035 | H28: 0.035 | I28: Assumption: low-single-digit same-store-sales-driven growth, in line with CBRL's recent 0.4%-0.8% reported growth plus modest sponsor-led initiatives.
A29: EBITDA margin, % of revenue | D29: 0.066 | E29: 0.069 | F29: 0.072 | G29: 0.075 | H29: 0.078 | I29: Assumption: margin expansion from FY25A 6.45% (224.3/3,480) toward ~7.8% by Year 5 via sponsor-driven cost initiatives (labor optimization, purchasing scale, G&A reduction) typical of a post-LBO 100-day value-creation plan.
A30: D&A, % of revenue | D30: 0.033 | E30: 0.033 | F30: 0.033 | G30: 0.033 | H30: 0.033 | I30: ESTIMATE — based off FY24A D&A of $111.0mm / $3,437mm revenue = 3.2%, rounded up slightly for continued capex reinvestment.
A31: Capital expenditures, % of revenue | D31: 0.037 | E31: 0.037 | F31: 0.037 | G31: 0.037 | H31: 0.037 | I31: Source basis: FY24A capex of $127.5mm / $3,437mm revenue = 3.7% (sourced); held flat.
A32: Increase in NWC, % of revenue growth | D32: 0.02 | E32: 0.02 | F32: 0.02 | G32: 0.02 | H32: 0.02 | I32: ESTIMATE — simplified NWC drag, applied to the dollar change in revenue (restaurant NWC needs are low; CBRL carries low receivables/inventory).
A33: Cash tax rate | D33: 0.26 | E33: 0.26 | F33: 0.26 | G33: 0.26 | H33: 0.26 | I33: Blended U.S. federal + state statutory-ish rate; higher than FY25A's unusually low 22.9% effective rate.
A35: EXIT ASSUMPTIONS
A36: Exit year (hold period, years) | C36: 5
A37: Exit EV/EBITDA multiple | C37: 9.5 | I37: Assumption: modest re-rating vs. the implied entry multiple (~9.2x), reflecting the margin improvement delivered over the hold period — not aggressive multiple arbitrage.
A38: Exit transaction fees, % of exit EV | C38: 0.015

Sheet Sources & Uses
A1: Sources & Uses of Funds at Close
A3: USES OF FUNDS
A4: Equity purchase price (offer price x diluted shares) | B4: =('Transaction Assumptions'!C6*'Transaction Assumptions'!C7) -> 1589.0179
A5: Refinance existing debt (FY2025A convertible notes) | B5: 484.6 | D5: Source: CBRL fiscal 2025 earnings release — total debt $484.6mm (0.625% converts due 2026 + 1.75% converts due 2030).
A6: Estimated transaction & financing fees | B6: =(B4+B5)*'Transaction Assumptions'!C25 -> 41.472359
A7: Total uses | B7: =SUM(B4:B6) -> 2115.0903
A9: SOURCES OF FUNDS
A10: Revolving credit facility (drawn at close) | B10: 0
A11: Term Loan A | B11: ='Transaction Assumptions'!C13*'Transaction Assumptions'!C8 -> 224.3
A12: Term Loan B | B12: ='Transaction Assumptions'!C14*'Transaction Assumptions'!C8 -> 448.6
A13: Senior Notes | B13: ='Transaction Assumptions'!C15*'Transaction Assumptions'!C8 -> 336.45
A14: Total new debt | B14: =SUM(B10:B13) -> 1009.35
A15: Cash from target balance sheet used at close | B15: 12 | D15: Source basis: CBRL FY2024A cash of $12.0mm (FY2025A figure not separately retrieved this session; held flat as a reasonable proxy).
A16: Sponsor equity contribution (plug) | B16: =B7-B14-B15 -> 1093.7403
A17: Total sources | B17: =SUM(B10:B13)+B15+B16 -> 2115.0903
A18: Check: sources = uses | B18: =B17-B7 -> 0
A20: TRANSACTION MULTIPLES & CAPITALIZATION
A21: Implied transaction enterprise value | B21: =B4+B5-B15 -> 2061.6179
A22: Existing net debt assumed / refinanced | B22: =B5-B15 -> 472.6
A23: Implied entry EV / FY2025A Adj. EBITDA | B23: =B21/'Transaction Assumptions'!C8 -> 9.1913417
A24: Total debt / FY2025A Adj. EBITDA (opening leverage) | B24: =B14/'Transaction Assumptions'!C8 -> 4.5
A25: Sponsor equity / total capitalization | B25: =B16/B17 -> 0.51711282

Sheet Debt Schedule
A1: Debt Schedule — 4-Tranche Post-LBO Capital Structure
A2: NOTE: Interest expense on each tranche is calculated on its BEGINNING-of-period balance (see Sources & Assumptions) so the mandatory amortization + cash-flow sweep waterfall stays fully dynamic without requiring iterative (circular) calculation.
C4: Entry (FY2026E) | D4: Year 1 (FY2027E) | E4: Year 2 (FY2028E) | F4: Year 3 (FY2029E) | G4: Year 4 (FY2030E) | H4: Year 5 / Exit (FY2031E)
A6: REVOLVING CREDIT FACILITY
A7: Beginning balance | C7: 0 | D7: =C9 -> 0 | E7: =D9 -> 11.111515 | F7: =E9 -> 3.9985947 | G7: =F9 -> 0 | H7: =G9 -> 0
A8: Draw / (paydown) | D8: =IF(D35<D36,MIN(D36-D35,'Transaction Assumptions'!$C$12-D7),-MIN(D7,MAX(0,D35-D36))) -> 11.111515 | E8: =IF(E35<E36,MIN(E36-E35,'Transaction Assumptions'!$C$12-E7),-MIN(E7,MAX(0,E35-E36))) -> -7.1129203 | F8: =IF(F35<F36,MIN(F36-F35,'Transaction Assumptions'!$C$12-F7),-MIN(F7,MAX(0,F35-F36))) -> -3.9985947 | G8: =IF(G35<G36,MIN(G36-G35,'Transaction Assumptions'!$C$12-G7),-MIN(G7,MAX(0,G35-G36))) -> 0 | H8: =IF(H35<H36,MIN(H36-H35,'Transaction Assumptions'!$C$12-H7),-MIN(H7,MAX(0,H35-H36))) -> 0
A9: Ending balance | C9: =C7 -> 0 | D9: =MAX(0,D7+D8) -> 11.111515 | E9: =MAX(0,E7+E8) -> 3.9985947 | F9: =MAX(0,F7+F8) -> 0 | G9: =MAX(0,G7+G8) -> 0 | H9: =MAX(0,H7+H8) -> 0
A10: Interest expense | C10: n/a | D10: =-D7*'Transaction Assumptions'!$C$20 -> 0 | E10: =-E7*'Transaction Assumptions'!$C$20 -> -0.75002726 | F10: =-F7*'Transaction Assumptions'!$C$20 -> -0.26990514 | G10: =-G7*'Transaction Assumptions'!$C$20 -> 0 | H10: =-H7*'Transaction Assumptions'!$C$20 -> 0
A12: TERM LOAN A
A13: Beginning balance | C13: ='Sources & Uses'!B11 -> 224.3 | D13: =C16 -> 224.3 | E13: =D16 -> 213.085 | F13: =E16 -> 201.87 | G13: =F16 -> 190.655 | H13: =G16 -> 179.44
A14: Mandatory amortization | C14: n/a | D14: =-MIN(D13,'Sources & Uses'!$B$11*'Transaction Assumptions'!$C$21) -> -11.215 | E14: =-MIN(E13,'Sources & Uses'!$B$11*'Transaction Assumptions'!$C$21) -> -11.215 | F14: =-MIN(F13,'Sources & Uses'!$B$11*'Transaction Assumptions'!$C$21) -> -11.215 | G14: =-MIN(G13,'Sources & Uses'!$B$11*'Transaction Assumptions'!$C$21) -> -11.215 | H14: =-MIN(H13,'Sources & Uses'!$B$11*'Transaction Assumptions'!$C$21) -> -11.215
A15: Cash sweep (post-TLB paydown) | C15: n/a | D15: =-MIN(MAX(D13+D14,0),MAX(D37-(-D22),0)) -> 0 | E15: =-MIN(MAX(E13+E14,0),MAX(E37-(-E22),0)) -> 0 | F15: =-MIN(MAX(F13+F14,0),MAX(F37-(-F22),0)) -> 0 | G15: =-MIN(MAX(G13+G14,0),MAX(G37-(-G22),0)) -> 0 | H15: =-MIN(MAX(H13+H14,0),MAX(H37-(-H22),0)) -> 0
A16: Ending balance | C16: =C13 -> 224.3 | D16: =MAX(0,D13+D14+D15) -> 213.085 | E16: =MAX(0,E13+E14+E15) -> 201.87 | F16: =MAX(0,F13+F14+F15) -> 190.655 | G16: =MAX(0,G13+G14+G15) -> 179.44 | H16: =MAX(0,H13+H14+H15) -> 168.225
A17: Interest expense | C17: n/a | D17: =-D13*'Transaction Assumptions'!$C$17 -> -15.701 | E17: =-E13*'Transaction Assumptions'!$C$17 -> -14.91595 | F17: =-F13*'Transaction Assumptions'!$C$17 -> -14.1309 | G17: =-G13*'Transaction Assumptions'!$C$17 -> -13.34585 | H17: =-H13*'Transaction Assumptions'!$C$17 -> -12.5608
A19: TERM LOAN B
A20: Beginning balance | C20: ='Sources & Uses'!B12 -> 448.6 | D20: =C23 -> 448.6 | E20: =D23 -> 444.114 | F20: =E23 -> 433.22637 | G20: =F23 -> 416.94668 | H20: =G23 -> 385.3932
A21: Mandatory amortization | C21: n/a | D21: =-MIN(D20,'Sources & Uses'!$B$12*'Transaction Assumptions'!$C$22) -> -4.486 | E21: =-MIN(E20,'Sources & Uses'!$B$12*'Transaction Assumptions'!$C$22) -> -4.486 | F21: =-MIN(F20,'Sources & Uses'!$B$12*'Transaction Assumptions'!$C$22) -> -4.486 | G21: =-MIN(G20,'Sources & Uses'!$B$12*'Transaction Assumptions'!$C$22) -> -4.486 | H21: =-MIN(H20,'Sources & Uses'!$B$12*'Transaction Assumptions'!$C$22) -> -4.486
A22: Cash sweep | C22: n/a | D22: =-MIN(MAX(D20+D21,0),D37) -> 0 | E22: =-MIN(MAX(E20+E21,0),E37) -> -6.4016283 | F22: =-MIN(MAX(F20+F21,0),F37) -> -11.793688 | G22: =-MIN(MAX(G20+G21,0),G37) -> -27.06748 | H22: =-MIN(MAX(H20+H21,0),H37) -> -45.70205
A23: Ending balance | C23: =C20 -> 448.6 | D23: =MAX(0,D20+D21+D22) -> 444.114 | E23: =MAX(0,E20+E21+E22) -> 433.22637 | F23: =MAX(0,F20+F21+F22) -> 416.94668 | G23: =MAX(0,G20+G21+G22) -> 385.3932 | H23: =MAX(0,H20+H21+H22) -> 335.20515
A24: Interest expense | C24: n/a | D24: =-D20*'Transaction Assumptions'!$C$18 -> -34.7665 | E24: =-E20*'Transaction Assumptions'!$C$18 -> -34.418835 | F24: =-F20*'Transaction Assumptions'!$C$18 -> -33.575044 | G24: =-G20*'Transaction Assumptions'!$C$18 -> -32.313368 | H24: =-H20*'Transaction Assumptions'!$C$18 -> -29.867973
A26: SENIOR NOTES (bullet, no amortization within hold period)
A27: Beginning balance | C27: ='Sources & Uses'!B13 -> 336.45 | D27: =C28 -> 336.45 | E27: =D28 -> 336.45 | F27: =E28 -> 336.45 | G27: =F28 -> 336.45 | H27: =G28 -> 336.45
A28: Ending balance | C28: =C27 -> 336.45 | D28: =D27 -> 336.45 | E28: =E27 -> 336.45 | F28: =F27 -> 336.45 | G28: =G27 -> 336.45 | H28: =H27 -> 336.45
A29: Interest expense | C29: n/a | D29: =-D28*'Transaction Assumptions'!$C$19 -> -28.59825 | E29: =-E28*'Transaction Assumptions'!$C$19 -> -28.59825 | F29: =-F28*'Transaction Assumptions'!$C$19 -> -28.59825 | G29: =-G28*'Transaction Assumptions'!$C$19 -> -28.59825 | H29: =-H28*'Transaction Assumptions'!$C$19 -> -28.59825
A31: CASH & SWEEP LOGIC
A32: Beginning cash balance | C32: n/a | D32: =C38 -> 12 | E32: =D38 -> 20 | F32: =E38 -> 13.598372 | G32: =F38 -> 17.311815 | H32: =G38 -> 23.007498
A33: Free cash flow before mandatory amortization & sweep | C33: n/a | D33: ='Operating Model'!D22 -> 12.589485 | E33: ='Operating Model'!E22 -> 22.81392 | F33: ='Operating Model'!F22 -> 35.206726 | G33: ='Operating Model'!G22 -> 48.464162 | H33: ='Operating Model'!H22 -> 63.473558
A34: Less: mandatory amortization (TLA + TLB) | C34: n/a | D34: =D14+D21 -> -15.701 | E34: =E14+E21 -> -15.701 | F34: =F14+F21 -> -15.701 | G34: =G14+G21 -> -15.701 | H34: =H14+H21 -> -15.701
A35: Cash available for discretionary sweep / revolver | C35: n/a | D35: =D32+D33+D34 -> 8.888485 | E35: =E32+E33+E34 -> 27.11292 | F35: =F32+F33+F34 -> 33.104098 | G35: =G32+G33+G34 -> 50.074978 | H35: =H32+H33+H34 -> 70.780055
A36: Minimum cash required | C36: ='Transaction Assumptions'!C24 -> 20 | D36: ='Transaction Assumptions'!$C$24 -> 20 | E36: ='Transaction Assumptions'!$C$24 -> 20 | F36: ='Transaction Assumptions'!$C$24 -> 20 | G36: ='Transaction Assumptions'!$C$24 -> 20 | H36: ='Transaction Assumptions'!$C$24 -> 20
A37: Cash flow swept to debt (TLB first, then TLA) | C37: n/a | D37: =MIN(MAX(0,D35-D36),(D20+D21+D13+D14))*'Transaction Assumptions'!$C$23 -> 0 | E37: =MIN(MAX(0,E35-E36),(E20+E21+E13+E14))*'Transaction Assumptions'!$C$23 -> 6.4016283 | F37: =MIN(MAX(0,F35-F36),(F20+F21+F13+F14))*'Transaction Assumptions'!$C$23 -> 11.793688 | G37: =MIN(MAX(0,G35-G36),(G20+G21+G13+G14))*'Transaction Assumptions'!$C$23 -> 27.06748 | H37: =MIN(MAX(0,H35-H36),(H20+H21+H13+H14))*'Transaction Assumptions'!$C$23 -> 45.70205
A38: Ending cash balance | C38: ='Sources & Uses'!B15 -> 12 | D38: =D35+D8-D37 -> 20 | E38: =E35+E8-E37 -> 13.598372 | F38: =F35+F8-F37 -> 17.311815 | G38: =G35+G8-G37 -> 23.007498 | H38: =H35+H8-H37 -> 25.078006
A40: Total debt (Revolver+TLA+TLB+Notes) | C40: =C9+C16+C23+C28 -> 1009.35 | D40: =D9+D16+D23+D28 -> 1004.7605 | E40: =E9+E16+E23+E28 -> 975.54497 | F40: =F9+F16+F23+F28 -> 944.05168 | G40: =G9+G16+G23+G28 -> 901.2832 | H40: =H9+H16+H23+H28 -> 839.88015
A41: Total interest expense | C41: n/a | D41: =D10+D17+D24+D29 -> -79.06575 | E41: =E10+E17+E24+E29 -> -78.683062 | F41: =F10+F17+F24+F29 -> -76.574099 | G41: =G10+G17+G24+G29 -> -74.257468 | H41: =H10+H17+H24+H29 -> -71.027023
A42: Net debt (total debt − cash) | C42: =C40-C38 -> 997.35 | D42: =D40-D38 -> 984.76052 | E42: =E40-E38 -> 961.94659 | F42: =F40-F38 -> 926.73987 | G42: =G40-G38 -> 878.27571 | H42: =H40-H38 -> 814.80215
A43: Net leverage (x LTM EBITDA) | C43: =C42/'Transaction Assumptions'!C8 -> 4.4465002 | D43: =D42/'Operating Model'!D9 -> 4.1829588 | E43: =E42/'Operating Model'!E9 -> 3.794561 | F43: =F42/'Operating Model'!F9 -> 3.4013223 | G43: =G42/'Operating Model'!G9 -> 2.9898658 | H43: =H42/'Operating Model'!H9 -> 2.5769103

Sheet Operating Model
A1: Post-LBO Operating Model & Free Cash Flow Build
C3: Entry (FY2026E) | D3: Year 1 (FY2027E) | E3: Year 2 (FY2028E) | F3: Year 3 (FY2029E) | G3: Year 4 (FY2030E) | H3: Year 5 / Exit (FY2031E)
A5: Revenue | C5: 3480 | D5: =C5*(1+'Transaction Assumptions'!D28) -> 3567 | E5: =D5*(1+'Transaction Assumptions'!E28) -> 3674.01 | F5: =E5*(1+'Transaction Assumptions'!F28) -> 3784.2303 | G5: =F5*(1+'Transaction Assumptions'!G28) -> 3916.6784 | H5: =G5*(1+'Transaction Assumptions'!H28) -> 4053.7621
A6: % growth YoY | D6: ='Transaction Assumptions'!D28 -> 0.025 | E6: ='Transaction Assumptions'!E28 -> 0.03 | F6: ='Transaction Assumptions'!F28 -> 0.03 | G6: ='Transaction Assumptions'!G28 -> 0.035 | H6: ='Transaction Assumptions'!H28 -> 0.035
A8: EBITDA margin % | C8: ='Transaction Assumptions'!C8/C5 -> 0.064454023 | D8: ='Transaction Assumptions'!D29 -> 0.066 | E8: ='Transaction Assumptions'!E29 -> 0.069 | F8: ='Transaction Assumptions'!F29 -> 0.072 | G8: ='Transaction Assumptions'!G29 -> 0.075 | H8: ='Transaction Assumptions'!H29 -> 0.078
A9: EBITDA | C9: ='Transaction Assumptions'!C8 -> 224.3 | D9: =D5*D8 -> 235.422 | E9: =E5*E8 -> 253.50669 | F9: =F5*F8 -> 272.46458 | G9: =G5*G8 -> 293.75088 | H9: =H5*H8 -> 316.19344
A11: Less: D&A | D11: =-D5*'Transaction Assumptions'!D30 -> -117.711 | E11: =-E5*'Transaction Assumptions'!E30 -> -121.24233 | F11: =-F5*'Transaction Assumptions'!F30 -> -124.8796 | G11: =-G5*'Transaction Assumptions'!G30 -> -129.25039 | H11: =-H5*'Transaction Assumptions'!H30 -> -133.77415
A12: EBIT | D12: =D9+D11 -> 117.711 | E12: =E9+E11 -> 132.26436 | F12: =F9+F11 -> 147.58498 | G12: =G9+G11 -> 164.50049 | H12: =H9+H11 -> 182.41929
A14: Less: total interest expense (net) | D14: ='Debt Schedule'!D41 -> -79.06575 | E14: ='Debt Schedule'!E41 -> -78.683062 | F14: ='Debt Schedule'!F41 -> -76.574099 | G14: ='Debt Schedule'!G41 -> -74.257468 | H14: ='Debt Schedule'!H41 -> -71.027023
A15: Pretax income | D15: =D12+D14 -> 38.64525 | E15: =E12+E14 -> 53.581298 | F15: =F12+F14 -> 71.010883 | G15: =G12+G14 -> 90.243023 | H15: =H12+H14 -> 111.39227
A16: Less: cash taxes | D16: =-MAX(0,D15)*'Transaction Assumptions'!D33 -> -10.047765 | E16: =-MAX(0,E15)*'Transaction Assumptions'!E33 -> -13.931137 | F16: =-MAX(0,F15)*'Transaction Assumptions'!F33 -> -18.46283 | G16: =-MAX(0,G15)*'Transaction Assumptions'!G33 -> -23.463186 | H16: =-MAX(0,H15)*'Transaction Assumptions'!H33 -> -28.961991
A17: Net income | D17: =D15+D16 -> 28.597485 | E17: =E15+E16 -> 39.65016 | F17: =F15+F16 -> 52.548053 | G17: =G15+G16 -> 66.779837 | H17: =H15+H16 -> 82.430281
A19: Plus: D&A (non-cash addback) | D19: =-D11 -> 117.711 | E19: =-E11 -> 121.24233 | F19: =-F11 -> 124.8796 | G19: =-G11 -> 129.25039 | H19: =-H11 -> 133.77415
A20: Less: capital expenditures | D20: =-D5*'Transaction Assumptions'!D31 -> -131.979 | E20: =-E5*'Transaction Assumptions'!E31 -> -135.93837 | F20: =-F5*'Transaction Assumptions'!F31 -> -140.01652 | G20: =-G5*'Transaction Assumptions'!G31 -> -144.9171 | H20: =-H5*'Transaction Assumptions'!H31 -> -149.9892
A21: Less: increase in net working capital | D21: =-(D5-C5)*'Transaction Assumptions'!D32 -> -1.74 | E21: =-(E5-D5)*'Transaction Assumptions'!E32 -> -2.1402 | F21: =-(F5-E5)*'Transaction Assumptions'!F32 -> -2.204406 | G21: =-(G5-F5)*'Transaction Assumptions'!G32 -> -2.6489612 | H21: =-(H5-G5)*'Transaction Assumptions'!H32 -> -2.7416749
A22: Free cash flow before mandatory amortization & sweep | D22: =D17+D19+D20+D21 -> 12.589485 | E22: =E17+E19+E20+E21 -> 22.81392 | F22: =F17+F19+F20+F21 -> 35.206726 | G22: =G17+G19+G20+G21 -> 48.464162 | H22: =H17+H19+H20+H21 -> 63.473558

Sheet Returns Analysis
A1: Returns Analysis — IRR / MOIC
A3: EXIT WATERFALL (base case: Year 5 / FY2031E exit)
A4: Exit year | C4: ='Transaction Assumptions'!C36 -> 5
A5: Exit-year EBITDA | C5: ='Operating Model'!H9 -> 316.19344
A6: Exit EV/EBITDA multiple | C6: ='Transaction Assumptions'!C37 -> 9.5
A7: Exit enterprise value | C7: =C5*C6 -> 3003.8377
A8: Less: exit transaction fees | C8: =-C7*'Transaction Assumptions'!C38 -> -45.057566
A9: Less: net debt at exit | C9: =-'Debt Schedule'!H42 -> -814.80215
A10: Exit equity value | C10: =C7+C8+C9 -> 2143.978
A12: RETURNS SUMMARY
A13: Entry sponsor equity investment | C13: ='Sources & Uses'!B16 -> 1093.7403
A14: Exit equity value | C14: =C10 -> 2143.978
A15: MOIC (multiple of invested capital) | C15: =C14/C13 -> 1.9602258
A16: IRR (5-year hold, no interim distributions) | C16: =(C15)^(1/C4)-1 -> 0.14409272
A17: Implied entry EV / FY2025A Adj. EBITDA | C17: ='Sources & Uses'!B23 -> 9.1913417
A18: Opening leverage (x EBITDA) | C18: ='Sources & Uses'!B24 -> 4.5
A19: Exit leverage (x EBITDA) | C19: ='Debt Schedule'!H43 -> 2.5769103
A21: SENSITIVITY 1 — IRR by Exit Year (rows) vs. Exit EV/EBITDA Multiple (columns)
B23: Exit Yr \ Multiple | C23: =$C$6+-2 -> 7.5 | D23: =$C$6+-1 -> 8.5 | E23: =$C$6+0 -> 9.5 | F23: =$C$6+1 -> 10.5 | G23: =$C$6+2 -> 11.5
B24: 3 | C24: =((('Operating Model'!F9*C$23)*(1-'Transaction Assumptions'!$C$38)-'Debt Schedule'!F42)/'Sources & Uses'!$B$16)^(1/3)-1 -> -0.0023363185 | D24: =((('Operating Model'!F9*D$23)*(1-'Transaction Assumptions'!$C$38)-'Debt Schedule'!F42)/'Sources & Uses'!$B$16)^(1/3)-1 -> 0.073869993 | E24: =((('Operating Model'!F9*E$23)*(1-'Transaction Assumptions'!$C$38)-'Debt Schedule'!F42)/'Sources & Uses'!$B$16)^(1/3)-1 -> 0.14056794 | F24: =((('Operating Model'!F9*F$23)*(1-'Transaction Assumptions'!$C$38)-'Debt Schedule'!F42)/'Sources & Uses'!$B$16)^(1/3)-1 -> 0.20026276 | G24: =((('Operating Model'!F9*G$23)*(1-'Transaction Assumptions'!$C$38)-'Debt Schedule'!F42)/'Sources & Uses'!$B$16)^(1/3)-1 -> 0.25454587
B25: 4 | C25: =((('Operating Model'!G9*C$23)*(1-'Transaction Assumptions'!$C$38)-'Debt Schedule'!G42)/'Sources & Uses'!$B$16)^(1/4)-1 -> 0.042487877 | D25: =((('Operating Model'!G9*D$23)*(1-'Transaction Assumptions'!$C$38)-'Debt Schedule'!G42)/'Sources & Uses'!$B$16)^(1/4)-1 -> 0.096515954 | E25: =((('Operating Model'!G9*E$23)*(1-'Transaction Assumptions'!$C$38)-'Debt Schedule'!G42)/'Sources & Uses'!$B$16)^(1/4)-1 -> 0.14356476 | F25: =((('Operating Model'!G9*F$23)*(1-'Transaction Assumptions'!$C$38)-'Debt Schedule'!G42)/'Sources & Uses'!$B$16)^(1/4)-1 -> 0.18543291 | G25: =((('Operating Model'!G9*G$23)*(1-'Transaction Assumptions'!$C$38)-'Debt Schedule'!G42)/'Sources & Uses'!$B$16)^(1/4)-1 -> 0.22328302
B26: 5 | C26: =((('Operating Model'!H9*C$23)*(1-'Transaction Assumptions'!$C$38)-'Debt Schedule'!H42)/'Sources & Uses'!$B$16)^(1/5)-1 -> 0.068187254 | D26: =((('Operating Model'!H9*D$23)*(1-'Transaction Assumptions'!$C$38)-'Debt Schedule'!H42)/'Sources & Uses'!$B$16)^(1/5)-1 -> 0.10873372 | E26: =((('Operating Model'!H9*E$23)*(1-'Transaction Assumptions'!$C$38)-'Debt Schedule'!H42)/'Sources & Uses'!$B$16)^(1/5)-1 -> 0.14409272 | F26: =((('Operating Model'!H9*F$23)*(1-'Transaction Assumptions'!$C$38)-'Debt Schedule'!H42)/'Sources & Uses'!$B$16)^(1/5)-1 -> 0.17555409 | G26: =((('Operating Model'!H9*G$23)*(1-'Transaction Assumptions'!$C$38)-'Debt Schedule'!H42)/'Sources & Uses'!$B$16)^(1/5)-1 -> 0.20396869
H27: Uses actual per-year EBITDA & net debt from the Debt Schedule; only exit year and exit multiple vary.
A29: SENSITIVITY 2 — IRR by Entry Offer Premium (rows) vs. Exit EV/EBITDA Multiple (columns)
A30: Simplification: the dollar amount of new debt raised and cash used at close are held fixed across premium scenarios (i.e., financing sized off EBITDA, not price paid) — only the sponsor's equity check flexes with the price paid. Exit-year economics use the base-case (30% premium) debt paydown path.
B32: Premium \ Multiple | C32: =$C$6+-2 -> 7.5 | D32: =$C$6+-1 -> 8.5 | E32: =$C$6+0 -> 9.5 | F32: =$C$6+1 -> 10.5 | G32: =$C$6+2 -> 11.5
B33: ='Transaction Assumptions'!$C$5+-0.15 -> 0.15 | C33: =((C10)/((('Transaction Assumptions'!$C$4*(1+$B33)*'Transaction Assumptions'!$C$7+'Sources & Uses'!$B$5)*(1+'Transaction Assumptions'!$C$25)-'Sources & Uses'!$B$14-'Sources & Uses'!$B$15)))^(1/$C$4)-1 -> 0.18781536 | D33: =((C10)/((('Transaction Assumptions'!$C$4*(1+$B33)*'Transaction Assumptions'!$C$7+'Sources & Uses'!$B$5)*(1+'Transaction Assumptions'!$C$25)-'Sources & Uses'!$B$14-'Sources & Uses'!$B$15)))^(1/$C$4)-1 -> 0.18781536 | E33: =((C10)/((('Transaction Assumptions'!$C$4*(1+$B33)*'Transaction Assumptions'!$C$7+'Sources & Uses'!$B$5)*(1+'Transaction Assumptions'!$C$25)-'Sources & Uses'!$B$14-'Sources & Uses'!$B$15)))^(1/$C$4)-1 -> 0.18781536 | F33: =((C10)/((('Transaction Assumptions'!$C$4*(1+$B33)*'Transaction Assumptions'!$C$7+'Sources & Uses'!$B$5)*(1+'Transaction Assumptions'!$C$25)-'Sources & Uses'!$B$14-'Sources & Uses'!$B$15)))^(1/$C$4)-1 -> 0.18781536 | G33: =((C10)/((('Transaction Assumptions'!$C$4*(1+$B33)*'Transaction Assumptions'!$C$7+'Sources & Uses'!$B$5)*(1+'Transaction Assumptions'!$C$25)-'Sources & Uses'!$B$14-'Sources & Uses'!$B$15)))^(1/$C$4)-1 -> 0.18781536
B34: ='Transaction Assumptions'!$C$5+-0.075 -> 0.225 | C34: =((C10)/((('Transaction Assumptions'!$C$4*(1+$B34)*'Transaction Assumptions'!$C$7+'Sources & Uses'!$B$5)*(1+'Transaction Assumptions'!$C$25)-'Sources & Uses'!$B$14-'Sources & Uses'!$B$15)))^(1/$C$4)-1 -> 0.16472622 | D34: =((C10)/((('Transaction Assumptions'!$C$4*(1+$B34)*'Transaction Assumptions'!$C$7+'Sources & Uses'!$B$5)*(1+'Transaction Assumptions'!$C$25)-'Sources & Uses'!$B$14-'Sources & Uses'!$B$15)))^(1/$C$4)-1 -> 0.16472622 | E34: =((C10)/((('Transaction Assumptions'!$C$4*(1+$B34)*'Transaction Assumptions'!$C$7+'Sources & Uses'!$B$5)*(1+'Transaction Assumptions'!$C$25)-'Sources & Uses'!$B$14-'Sources & Uses'!$B$15)))^(1/$C$4)-1 -> 0.16472622 | F34: =((C10)/((('Transaction Assumptions'!$C$4*(1+$B34)*'Transaction Assumptions'!$C$7+'Sources & Uses'!$B$5)*(1+'Transaction Assumptions'!$C$25)-'Sources & Uses'!$B$14-'Sources & Uses'!$B$15)))^(1/$C$4)-1 -> 0.16472622 | G34: =((C10)/((('Transaction Assumptions'!$C$4*(1+$B34)*'Transaction Assumptions'!$C$7+'Sources & Uses'!$B$5)*(1+'Transaction Assumptions'!$C$25)-'Sources & Uses'!$B$14-'Sources & Uses'!$B$15)))^(1/$C$4)-1 -> 0.16472622
B35: ='Transaction Assumptions'!$C$5+0 -> 0.3 | C35: =((C10)/((('Transaction Assumptions'!$C$4*(1+$B35)*'Transaction Assumptions'!$C$7+'Sources & Uses'!$B$5)*(1+'Transaction Assumptions'!$C$25)-'Sources & Uses'!$B$14-'Sources & Uses'!$B$15)))^(1/$C$4)-1 -> 0.14409272 | D35: =((C10)/((('Transaction Assumptions'!$C$4*(1+$B35)*'Transaction Assumptions'!$C$7+'Sources & Uses'!$B$5)*(1+'Transaction Assumptions'!$C$25)-'Sources & Uses'!$B$14-'Sources & Uses'!$B$15)))^(1/$C$4)-1 -> 0.14409272 | E35: =((C10)/((('Transaction Assumptions'!$C$4*(1+$B35)*'Transaction Assumptions'!$C$7+'Sources & Uses'!$B$5)*(1+'Transaction Assumptions'!$C$25)-'Sources & Uses'!$B$14-'Sources & Uses'!$B$15)))^(1/$C$4)-1 -> 0.14409272 | F35: =((C10)/((('Transaction Assumptions'!$C$4*(1+$B35)*'Transaction Assumptions'!$C$7+'Sources & Uses'!$B$5)*(1+'Transaction Assumptions'!$C$25)-'Sources & Uses'!$B$14-'Sources & Uses'!$B$15)))^(1/$C$4)-1 -> 0.14409272 | G35: =((C10)/((('Transaction Assumptions'!$C$4*(1+$B35)*'Transaction Assumptions'!$C$7+'Sources & Uses'!$B$5)*(1+'Transaction Assumptions'!$C$25)-'Sources & Uses'!$B$14-'Sources & Uses'!$B$15)))^(1/$C$4)-1 -> 0.14409272
B36: ='Transaction Assumptions'!$C$5+0.075 -> 0.375 | C36: =((C10)/((('Transaction Assumptions'!$C$4*(1+$B36)*'Transaction Assumptions'!$C$7+'Sources & Uses'!$B$5)*(1+'Transaction Assumptions'!$C$25)-'Sources & Uses'!$B$14-'Sources & Uses'!$B$15)))^(1/$C$4)-1 -> 0.12547482 | D36: =((C10)/((('Transaction Assumptions'!$C$4*(1+$B36)*'Transaction Assumptions'!$C$7+'Sources & Uses'!$B$5)*(1+'Transaction Assumptions'!$C$25)-'Sources & Uses'!$B$14-'Sources & Uses'!$B$15)))^(1/$C$4)-1 -> 0.12547482 | E36: =((C10)/((('Transaction Assumptions'!$C$4*(1+$B36)*'Transaction Assumptions'!$C$7+'Sources & Uses'!$B$5)*(1+'Transaction Assumptions'!$C$25)-'Sources & Uses'!$B$14-'Sources & Uses'!$B$15)))^(1/$C$4)-1 -> 0.12547482 | F36: =((C10)/((('Transaction Assumptions'!$C$4*(1+$B36)*'Transaction Assumptions'!$C$7+'Sources & Uses'!$B$5)*(1+'Transaction Assumptions'!$C$25)-'Sources & Uses'!$B$14-'Sources & Uses'!$B$15)))^(1/$C$4)-1 -> 0.12547482 | G36: =((C10)/((('Transaction Assumptions'!$C$4*(1+$B36)*'Transaction Assumptions'!$C$7+'Sources & Uses'!$B$5)*(1+'Transaction Assumptions'!$C$25)-'Sources & Uses'!$B$14-'Sources & Uses'!$B$15)))^(1/$C$4)-1 -> 0.12547482
B37: ='Transaction Assumptions'!$C$5+0.15 -> 0.45 | C37: =((C10)/((('Transaction Assumptions'!$C$4*(1+$B37)*'Transaction Assumptions'!$C$7+'Sources & Uses'!$B$5)*(1+'Transaction Assumptions'!$C$25)-'Sources & Uses'!$B$14-'Sources & Uses'!$B$15)))^(1/$C$4)-1 -> 0.1085386 | D37: =((C10)/((('Transaction Assumptions'!$C$4*(1+$B37)*'Transaction Assumptions'!$C$7+'Sources & Uses'!$B$5)*(1+'Transaction Assumptions'!$C$25)-'Sources & Uses'!$B$14-'Sources & Uses'!$B$15)))^(1/$C$4)-1 -> 0.1085386 | E37: =((C10)/((('Transaction Assumptions'!$C$4*(1+$B37)*'Transaction Assumptions'!$C$7+'Sources & Uses'!$B$5)*(1+'Transaction Assumptions'!$C$25)-'Sources & Uses'!$B$14-'Sources & Uses'!$B$15)))^(1/$C$4)-1 -> 0.1085386 | F37: =((C10)/((('Transaction Assumptions'!$C$4*(1+$B37)*'Transaction Assumptions'!$C$7+'Sources & Uses'!$B$5)*(1+'Transaction Assumptions'!$C$25)-'Sources & Uses'!$B$14-'Sources & Uses'!$B$15)))^(1/$C$4)-1 -> 0.1085386 | G37: =((C10)/((('Transaction Assumptions'!$C$4*(1+$B37)*'Transaction Assumptions'!$C$7+'Sources & Uses'!$B$5)*(1+'Transaction Assumptions'!$C$25)-'Sources & Uses'!$B$14-'Sources & Uses'!$B$15)))^(1/$C$4)-1 -> 0.1085386

Sheet Sources & Assumptions
A1: Sources & Assumptions — Full Disclosure
A3: This is a HYPOTHETICAL sponsor buyout — no such transaction has been announced for Cracker Barrel. The target's real FY2024A/FY2025A financials anchor the model; the transaction structure, financing terms and operating projections are illustrative analyst assumptions. Direct access to SEC EDGAR / stockanalysis.com / press-release wires was blocked by this session's network egress policy, so every 'SOURCED' figure below was obtained via search-engine synthesis of the underlying filings/releases rather than a direct read of the primary document.
A5: # | B5: Item | C5: Detail / Citation
A6: SOURCED | B6: FY2025A revenue | C6: $3.48bn, +0.4% YoY (or +2.2% adjusted for a prior-year 53rd week) — Cracker Barrel fiscal Q4/full-year 2025 earnings release.
A7: SOURCED | B7: FY2025A Adjusted EBITDA | C7: $224.3mm, +9% YoY — Cracker Barrel fiscal Q4/full-year 2025 earnings release.
A8: SOURCED | B8: FY2025A GAAP operating income / net income | C8: $75.09mm / $46.4mm; interest expense, net $20.489mm; effective tax rate ~22.9% — fiscal 2025 earnings release (via search synthesis).
A9: SOURCED | B9: FY2025A total debt & leverage | C9: $484.6mm (0.625% convertible notes due 2026, $149.2mm + 1.75% convertible notes due 2030, $335.4mm); consolidated total leverage ratio 2.0x; available liquidity $555.6mm.
A10: SOURCED | B10: FY2024A balance sheet detail | C10: Cash $12.0mm, AR $39.2mm, inventory $181.0mm, net PP&E $959.8mm, total assets $2,161.5mm, AP $162.3mm, LT debt $476.6mm, total equity $440.1mm — FY2024 Form 10-K (period ended 8/2/2024, via search synthesis).
A11: SOURCED | B11: FY2024A capex & D&A | C11: Capital expenditures (net of insurance recoveries) $127.5mm; depreciation $111.0mm — FY2024 Form 10-K.
A12: SOURCED | B12: Share price & share count | C12: $54.69/share; ~22.35mm diluted shares (~$1.22-1.26bn market cap) — 2025/2026 market data.
A13: ESTIMATE | B13: FY2025A cash, capex, D&A | C13: Exact FY2025 fiscal-year-end balance sheet / cash-flow-statement figures were not retrieved this session (only partial-year 10-Q data surfaced in search). FY2024A actuals are used as the closest available proxy where a FY2025A figure was not confirmed — see individual cells for detail.
A14: ASSUMPTION | B14: 30% offer premium -> $71.10/share offer price | C14: Illustrative premium in line with recent going-private consumer/restaurant transactions (typically 25%-40% to undisturbed price). Not based on any actual proposal for CBRL.
A15: ASSUMPTION | B15: 4.5x total entry leverage (1.0x TLA / 2.0x TLB / 1.5x Notes) | C15: Illustrative, moderate sponsor capital structure for a real-estate-heavy restaurant chain — CBRL's owned real estate (~$960mm net PP&E FY24A) provides incremental collateral value / sale-leaseback optionality supporting this leverage level. Flex on the Transaction Assumptions tab to stress-test a more aggressive (5.5x+) or conservative (3.5x) structure.
A16: ASSUMPTION | B16: Debt pricing (TLA 7.00%, TLB 7.75%, Notes 8.50%, Revolver 6.75%) | C16: Illustrative spreads over a ~4.3% SOFR proxy, consistent with a ~4.5x-levered, sub-investment-grade sponsor financing in the Sept-2026 rate environment.
... A21: METHODOLOGY | B21: Sensitivity 2 (IRR by entry premium) | C21: A fully-dynamic re-solve of the circular debt schedule for every premium scenario is impractical in a static spreadsheet grid, so this table holds the DOLLAR AMOUNT of new debt and cash used at close fixed across scenarios (i.e., financing is sized off EBITDA, consistent with real leveraged-loan market practice) and flexes only the sponsor equity check and resulting IRR/MOIC. This is a standard simplification but should not be read as a fully re-run scenario the way Sensitivity 1 (exit year x exit multiple, which uses the model's actual per-year figures) is.
